[{"code_region":"84","libelle_region":"Auvergne-Rhône-Alpes","code_departement":"43","libelle_departement":"Haute-Loire","code_commune":"43001","libelle_commune":"Agnat","inscrits":155,"abstentions":75,"votants":80,"blancs":2,"nuls":2,"exprimes":76,"ratio_abstentions_inscrits":48.39,"ratio_votants_inscrits":51.61,"ratio_exprimes_votants":95.0},{"code_region":"84","libelle_region":"Auvergne-Rhône-Alpes","code_departement":"43","libelle_departement":"Haute-Loire","code_commune":"43002","libelle_commune":"Aiguilhe","inscrits":1141,"abstentions":490,"votants":651,"blancs":10,"nuls":17,"exprimes":624,"ratio_abstentions_inscrits":42.94,"ratio_votants_inscrits":57.06,"ratio_exprimes_votants":95.85},{"code_region":"84","libelle_region":"Auvergne-Rhône-Alpes","code_departement":"43","libelle_departement":"Haute-Loire","code_commune":"43003","libelle_commune":"Allègre","inscrits":624,"abstentions":255,"votants":369,"blancs":6,"nuls":11,"exprimes":352,"ratio_abstentions_inscrits":40.87,"ratio_votants_inscrits":59.13,"ratio_exprimes_votants":95.39},{"code_region":"84","libelle_region":"Auvergne-Rhône-Alpes","code_departement":"43","libelle_departement":"Haute-Loire","code_commune":"43004","libelle_commune":"Alleyrac","inscrits":148,"abstentions":56,"votants":92,"blancs":1,"nuls":2,"exprimes":89,"ratio_abstentions_inscrits":37.84,"ratio_votants_inscrits":62.16,"ratio_exprimes_votants":96.74},{"code_region":"84","libelle_region":"Auvergne-Rhône-Alpes","code_departement":"43","libelle_departement":"Haute-Loire","code_commune":"43005","libelle_commune":"Alleyras","inscrits":198,"abstentions":80,"votants":118,"blancs":1,"nuls":7,"exprimes":110,"ratio_abstentions_inscrits":40.4,"ratio_votants_inscrits":59.6,"ratio_exprimes_votants":93.22},{"code_region":"84","libelle_region":"Auvergne-Rhône-Alpes","code_departement":"43","libelle_departement":"Haute-Loire","code_commune":"43006","libelle_commune":"Ally","inscrits":152,"abstentions":68,"votants":84,"blancs":2,"nuls":2,"exprimes":80,"ratio_abstentions_inscrits":44.74,"ratio_votants_inscrits":55.26,"ratio_exprimes_votants":95.24},{"code_region":"84","libelle_region":"Auvergne-Rhône-Alpes","code_departement":"43","libelle_departement":"Haute-Loire","code_commune":"43007","libelle_commune":"Araules","inscrits":593,"abstentions":250,"votants":343,"blancs":9,"nuls":12,"exprimes":322,"ratio_abstentions_inscrits":42.16,"ratio_votants_inscrits":57.84,"ratio_exprimes_votants":93.88},{"code_region":"84","libelle_region":"Auvergne-Rhône-Alpes","code_departement":"43","libelle_departement":"Haute-Loire","code_commune":"43008","libelle_commune":"Arlempdes","inscrits":156,"abstentions":54,"votants":102,"blancs":2,"nuls":3,"exprimes":97,"ratio_abstentions_inscrits":34.62,"ratio_votants_inscrits":65.38,"ratio_exprimes_votants":95.1},{"code_region":"84","libelle_region":"Auvergne-Rhône-Alpes","code_departement":"43","libelle_departement":"Haute-Loire","code_commune":"43009","libelle_commune":"Arlet","inscrits":26,"abstentions":5,"votants":21,"blancs":0,"nuls":0,"exprimes":21,"ratio_abstentions_inscrits":19.23,"ratio_votants_inscrits":80.77,"ratio_exprimes_votants":100.0},{"code_region":"84","libelle_region":"Auvergne-Rhône-Alpes","code_departement":"43","libelle_departement":"Haute-Loire","code_commune":"43010","libelle_commune":"Arsac-En-Velay","inscrits":971,"abstentions":401,"votants":570,"blancs":8,"nuls":15,"exprimes":547,"ratio_abstentions_inscrits":41.3,"ratio_votants_inscrits":58.7,"ratio_exprimes_votants":95.96},{"code_region":"84","libelle_region":"Auvergne-Rhône-Alpes","code_departement":"43","libelle_departement":"Haute-Loire","code_commune":"43011","libelle_commune":"Aubazat","inscrits":170,"abstentions":65,"votants":105,"blancs":1,"nuls":2,"exprimes":102,"ratio_abstentions_inscrits":38.24,"ratio_votants_inscrits":61.76,"ratio_exprimes_votants":97.14},{"code_region":"84","libelle_region":"Auvergne-Rhône-Alpes","code_departement":"43","libelle_departement":"Haute-Loire","code_commune":"43012","libelle_commune":"Aurec-Sur-Loire","inscrits":4790,"abstentions":2071,"votants":2719,"blancs":33,"nuls":45,"exprimes":2641,"ratio_abstentions_inscrits":43.24,"ratio_votants_inscrits":56.76,"ratio_exprimes_votants":97.13},{"code_region":"84","libelle_region":"Auvergne-Rhône-Alpes","code_departement":"43","libelle_departement":"Haute-Loire","code_commune":"43013","libelle_commune":"Vissac-Auteyrac","inscrits":325,"abstentions":121,"votants":204,"blancs":5,"nuls":6,"exprimes":193,"ratio_abstentions_inscrits":37.23,"ratio_votants_inscrits":62.77,"ratio_exprimes_votants":94.61},{"code_region":"84","libelle_region":"Auvergne-Rhône-Alpes","code_departement":"43","libelle_departement":"Haute-Loire","code_commune":"43014","libelle_commune":"Autrac","inscrits":52,"abstentions":13,"votants":39,"blancs":1,"nuls":0,"exprimes":38,"ratio_abstentions_inscrits":25.0,"ratio_votants_inscrits":75.0,"ratio_exprimes_votants":97.44},{"code_region":"84","libelle_region":"Auvergne-Rhône-Alpes","code_departement":"43","libelle_departement":"Haute-Loire","code_commune":"43015","libelle_commune":"Auvers","inscrits":59,"abstentions":26,"votants":33,"blancs":0,"nuls":1,"exprimes":32,"ratio_abstentions_inscrits":44.07,"ratio_votants_inscrits":55.93,"ratio_exprimes_votants":96.97},{"code_region":"84","libelle_region":"Auvergne-Rhône-Alpes","code_departement":"43","libelle_departement":"Haute-Loire","code_commune":"43016","libelle_commune":"Auzon","inscrits":694,"abstentions":327,"votants":367,"blancs":5,"nuls":11,"exprimes":351,"ratio_abstentions_inscrits":47.12,"ratio_votants_inscrits":52.88,"ratio_exprimes_votants":95.64},{"code_region":"84","libelle_region":"Auvergne-Rhône-Alpes","code_departement":"43","libelle_departement":"Haute-Loire","code_commune":"43017","libelle_commune":"Azérat","inscrits":240,"abstentions":97,"votants":143,"blancs":6,"nuls":3,"exprimes":134,"ratio_abstentions_inscrits":40.42,"ratio_votants_inscrits":59.58,"ratio_exprimes_votants":93.71},{"code_region":"84","libelle_region":"Auvergne-Rhône-Alpes","code_departement":"43","libelle_departement":"Haute-Loire","code_commune":"43018","libelle_commune":"Bains","inscrits":941,"abstentions":357,"votants":584,"blancs":21,"nuls":15,"exprimes":548,"ratio_abstentions_inscrits":37.94,"ratio_votants_inscrits":62.06,"ratio_exprimes_votants":93.84},{"code_region":"84","libelle_region":"Auvergne-Rhône-Alpes","code_departement":"43","libelle_departement":"Haute-Loire","code_commune":"43019","libelle_commune":"Barges","inscrits":89,"abstentions":23,"votants":66,"blancs":0,"nuls":1,"exprimes":65,"ratio_abstentions_inscrits":25.84,"ratio_votants_inscrits":74.16,"ratio_exprimes_votants":98.48},{"code_region":"84","libelle_region":"Auvergne-Rhône-Alpes","code_departement":"43","libelle_departement":"Haute-Loire","code_commune":"43020","libelle_commune":"Bas-En-Basset","inscrits":3624,"abstentions":1564,"votants":2060,"blancs":35,"nuls":22,"exprimes":2003,"ratio_abstentions_inscrits":43.16,"ratio_votants_inscrits":56.84,"ratio_exprimes_votants":97.23},{"code_region":"84","libelle_region":"Auvergne-Rhône-Alpes","code_departement":"43","libelle_departement":"Haute-Loire","code_commune":"43021","libelle_commune":"Beaulieu","inscrits":841,"abstentions":356,"votants":485,"blancs":8,"nuls":10,"exprimes":467,"ratio_abstentions_inscrits":42.33,"ratio_votants_inscrits":57.67,"ratio_exprimes_votants":96.29},{"code_region":"84","libelle_region":"Auvergne-Rhône-Alpes","code_departement":"43","libelle_departement":"Haute-Loire","code_commune":"43022","libelle_commune":"Beaumont","inscrits":246,"abstentions":96,"votants":150,"blancs":4,"nuls":5,"exprimes":141,"ratio_abstentions_inscrits":39.02,"ratio_votants_inscrits":60.98,"ratio_exprimes_votants":94.0},{"code_region":"84","libelle_region":"Auvergne-Rhône-Alpes","code_departement":"43","libelle_departement":"Haute-Loire","code_commune":"43023","libelle_commune":"Beaune-Sur-Arzon","inscrits":222,"abstentions":89,"votants":133,"blancs":3,"nuls":5,"exprimes":125,"ratio_abstentions_inscrits":40.09,"ratio_votants_inscrits":59.91,"ratio_exprimes_votants":93.98},{"code_region":"84","libelle_region":"Auvergne-Rhône-Alpes","code_departement":"43","libelle_departement":"Haute-Loire","code_commune":"43024","libelle_commune":"Beaux","inscrits":689,"abstentions":273,"votants":416,"blancs":9,"nuls":13,"exprimes":394,"ratio_abstentions_inscrits":39.62,"ratio_votants_inscrits":60.38,"ratio_exprimes_votants":94.71},{"code_region":"84","libelle_region":"Auvergne-Rhône-Alpes","code_departement":"43","libelle_departement":"Haute-Loire","code_commune":"43025","libelle_commune":"Beauzac","inscrits":2299,"abstentions":951,"votants":1348,"blancs":39,"nuls":28,"exprimes":1281,"ratio_abstentions_inscrits":41.37,"ratio_votants_inscrits":58.63,"ratio_exprimes_votants":95.03},{"code_region":"84","libelle_region":"Auvergne-Rhône-Alpes","code_departement":"43","libelle_departement":"Haute-Loire","code_commune":"43026","libelle_commune":"Bellevue-La-Montagne","inscrits":443,"abstentions":191,"votants":252,"blancs":2,"nuls":7,"exprimes":243,"ratio_abstentions_inscrits":43.12,"ratio_votants_inscrits":56.88,"ratio_exprimes_votants":96.43},{"code_region":"84","libelle_region":"Auvergne-Rhône-Alpes","code_departement":"43","libelle_departement":"Haute-Loire","code_commune":"43027","libelle_commune":"Berbezit","inscrits":55,"abstentions":19,"votants":36,"blancs":2,"nuls":0,"exprimes":34,"ratio_abstentions_inscrits":34.55,"ratio_votants_inscrits":65.45,"ratio_exprimes_votants":94.44},{"code_region":"84","libelle_region":"Auvergne-Rhône-Alpes","code_departement":"43","libelle_departement":"Haute-Loire","code_commune":"43028","libelle_commune":"Bessamorel","inscrits":383,"abstentions":153,"votants":230,"blancs":6,"nuls":7,"exprimes":217,"ratio_abstentions_inscrits":39.95,"ratio_votants_inscrits":60.05,"ratio_exprimes_votants":94.35},{"code_region":"84","libelle_region":"Auvergne-Rhône-Alpes","code_departement":"43","libelle_departement":"Haute-Loire","code_commune":"43029","libelle_commune":"La Besseyre-Saint-Mary","inscrits":116,"abstentions":53,"votants":63,"blancs":3,"nuls":4,"exprimes":56,"ratio_abstentions_inscrits":45.69,"ratio_votants_inscrits":54.31,"ratio_exprimes_votants":88.89},{"code_region":"84","libelle_region":"Auvergne-Rhône-Alpes","code_departement":"43","libelle_departement":"Haute-Loire","code_commune":"43030","libelle_commune":"Blanzac","inscrits":356,"abstentions":124,"votants":232,"blancs":15,"nuls":9,"exprimes":208,"ratio_abstentions_inscrits":34.83,"ratio_votants_inscrits":65.17,"ratio_exprimes_votants":89.66},{"code_region":"84","libelle_region":"Auvergne-Rhône-Alpes","code_departement":"43","libelle_departement":"Haute-Loire","code_commune":"43031","libelle_commune":"Blassac","inscrits":135,"abstentions":50,"votants":85,"blancs":0,"nuls":5,"exprimes":80,"ratio_abstentions_inscrits":37.04,"ratio_votants_inscrits":62.96,"ratio_exprimes_votants":94.12},{"code_region":"84","libelle_region":"Auvergne-Rhône-Alpes","code_departement":"43","libelle_departement":"Haute-Loire","code_commune":"43032","libelle_commune":"Blavozy","inscrits":1401,"abstentions":612,"votants":789,"blancs":19,"nuls":15,"exprimes":755,"ratio_abstentions_inscrits":43.68,"ratio_votants_inscrits":56.32,"ratio_exprimes_votants":95.69},{"code_region":"84","libelle_region":"Auvergne-Rhône-Alpes","code_departement":"43","libelle_departement":"Haute-Loire","code_commune":"43033","libelle_commune":"Blesle","inscrits":575,"abstentions":211,"votants":364,"blancs":12,"nuls":13,"exprimes":339,"ratio_abstentions_inscrits":36.7,"ratio_votants_inscrits":63.3,"ratio_exprimes_votants":93.13},{"code_region":"84","libelle_region":"Auvergne-Rhône-Alpes","code_departement":"43","libelle_departement":"Haute-Loire","code_commune":"43034","libelle_commune":"Boisset","inscrits":321,"abstentions":113,"votants":208,"blancs":4,"nuls":9,"exprimes":195,"ratio_abstentions_inscrits":35.2,"ratio_votants_inscrits":64.8,"ratio_exprimes_votants":93.75},{"code_region":"84","libelle_region":"Auvergne-Rhône-Alpes","code_departement":"43","libelle_departement":"Haute-Loire","code_commune":"43035","libelle_commune":"Bonneval","inscrits":76,"abstentions":28,"votants":48,"blancs":0,"nuls":3,"exprimes":45,"ratio_abstentions_inscrits":36.84,"ratio_votants_inscrits":63.16,"ratio_exprimes_votants":93.75},{"code_region":"84","libelle_region":"Auvergne-Rhône-Alpes","code_departement":"43","libelle_departement":"Haute-Loire","code_commune":"43036","libelle_commune":"Borne","inscrits":340,"abstentions":122,"votants":218,"blancs":3,"nuls":6,"exprimes":209,"ratio_abstentions_inscrits":35.88,"ratio_votants_inscrits":64.12,"ratio_exprimes_votants":95.87},{"code_region":"84","libelle_region":"Auvergne-Rhône-Alpes","code_departement":"43","libelle_departement":"Haute-Loire","code_commune":"43037","libelle_commune":"Le Bouchet-Saint-Nicolas","inscrits":248,"abstentions":52,"votants":196,"blancs":2,"nuls":6,"exprimes":188,"ratio_abstentions_inscrits":20.97,"ratio_votants_inscrits":79.03,"ratio_exprimes_votants":95.92},{"code_region":"84","libelle_region":"Auvergne-Rhône-Alpes","code_departement":"43","libelle_departement":"Haute-Loire","code_commune":"43038","libelle_commune":"Bournoncle-Saint-Pierre","inscrits":821,"abstentions":386,"votants":435,"blancs":23,"nuls":8,"exprimes":404,"ratio_abstentions_inscrits":47.02,"ratio_votants_inscrits":52.98,"ratio_exprimes_votants":92.87},{"code_region":"84","libelle_region":"Auvergne-Rhône-Alpes","code_departement":"43","libelle_departement":"Haute-Loire","code_commune":"43039","libelle_commune":"Le Brignon","inscrits":527,"abstentions":242,"votants":285,"blancs":6,"nuls":7,"exprimes":272,"ratio_abstentions_inscrits":45.92,"ratio_votants_inscrits":54.08,"ratio_exprimes_votants":95.44},{"code_region":"84","libelle_region":"Auvergne-Rhône-Alpes","code_departement":"43","libelle_departement":"Haute-Loire","code_commune":"43040","libelle_commune":"Brioude","inscrits":4836,"abstentions":2454,"votants":2382,"blancs":37,"nuls":57,"exprimes":2288,"ratio_abstentions_inscrits":50.74,"ratio_votants_inscrits":49.26,"ratio_exprimes_votants":96.05},{"code_region":"84","libelle_region":"Auvergne-Rhône-Alpes","code_departement":"43","libelle_departement":"Haute-Loire","code_commune":"43041","libelle_commune":"Brives-Charensac","inscrits":3027,"abstentions":1363,"votants":1664,"blancs":28,"nuls":31,"exprimes":1605,"ratio_abstentions_inscrits":45.03,"ratio_votants_inscrits":54.97,"ratio_exprimes_votants":96.45},{"code_region":"84","libelle_region":"Auvergne-Rhône-Alpes","code_departement":"43","libelle_departement":"Haute-Loire","code_commune":"43042","libelle_commune":"Cayres","inscrits":597,"abstentions":218,"votants":379,"blancs":8,"nuls":11,"exprimes":360,"ratio_abstentions_inscrits":36.52,"ratio_votants_inscrits":63.48,"ratio_exprimes_votants":94.99},{"code_region":"84","libelle_region":"Auvergne-Rhône-Alpes","code_departement":"43","libelle_departement":"Haute-Loire","code_commune":"43043","libelle_commune":"Céaux-D'Allègre","inscrits":401,"abstentions":167,"votants":234,"blancs":7,"nuls":2,"exprimes":225,"ratio_abstentions_inscrits":41.65,"ratio_votants_inscrits":58.35,"ratio_exprimes_votants":96.15},{"code_region":"84","libelle_region":"Auvergne-Rhône-Alpes","code_departement":"43","libelle_departement":"Haute-Loire","code_commune":"43044","libelle_commune":"Cerzat","inscrits":197,"abstentions":70,"votants":127,"blancs":3,"nuls":1,"exprimes":123,"ratio_abstentions_inscrits":35.53,"ratio_votants_inscrits":64.47,"ratio_exprimes_votants":96.85},{"code_region":"84","libelle_region":"Auvergne-Rhône-Alpes","code_departement":"43","libelle_departement":"Haute-Loire","code_commune":"43045","libelle_commune":"Ceyssac","inscrits":317,"abstentions":119,"votants":198,"blancs":4,"nuls":4,"exprimes":190,"ratio_abstentions_inscrits":37.54,"ratio_votants_inscrits":62.46,"ratio_exprimes_votants":95.96},{"code_region":"84","libelle_region":"Auvergne-Rhône-Alpes","code_departement":"43","libelle_departement":"Haute-Loire","code_commune":"43046","libelle_commune":"Chadrac","inscrits":2010,"abstentions":820,"votants":1190,"blancs":18,"nuls":32,"exprimes":1140,"ratio_abstentions_inscrits":40.8,"ratio_votants_inscrits":59.2,"ratio_exprimes_votants":95.8},{"code_region":"84","libelle_region":"Auvergne-Rhône-Alpes","code_departement":"43","libelle_departement":"Haute-Loire","code_commune":"43047","libelle_commune":"Chadron","inscrits":259,"abstentions":90,"votants":169,"blancs":7,"nuls":2,"exprimes":160,"ratio_abstentions_inscrits":34.75,"ratio_votants_inscrits":65.25,"ratio_exprimes_votants":94.67},{"code_region":"84","libelle_region":"Auvergne-Rhône-Alpes","code_departement":"43","libelle_departement":"Haute-Loire","code_commune":"43048","libelle_commune":"La Chaise-Dieu","inscrits":526,"abstentions":238,"votants":288,"blancs":6,"nuls":2,"exprimes":280,"ratio_abstentions_inscrits":45.25,"ratio_votants_inscrits":54.75,"ratio_exprimes_votants":97.22},{"code_region":"84","libelle_region":"Auvergne-Rhône-Alpes","code_departement":"43","libelle_departement":"Haute-Loire","code_commune":"43049","libelle_commune":"Chamalières-Sur-Loire","inscrits":432,"abstentions":164,"votants":268,"blancs":2,"nuls":4,"exprimes":262,"ratio_abstentions_inscrits":37.96,"ratio_votants_inscrits":62.04,"ratio_exprimes_votants":97.76},{"code_region":"84","libelle_region":"Auvergne-Rhône-Alpes","code_departement":"43","libelle_departement":"Haute-Loire","code_commune":"43050","libelle_commune":"Chambezon","inscrits":87,"abstentions":30,"votants":57,"blancs":0,"nuls":3,"exprimes":54,"ratio_abstentions_inscrits":34.48,"ratio_votants_inscrits":65.52,"ratio_exprimes_votants":94.74},{"code_region":"84","libelle_region":"Auvergne-Rhône-Alpes","code_departement":"43","libelle_departement":"Haute-Loire","code_commune":"43051","libelle_commune":"Le Chambon-Sur-Lignon","inscrits":2255,"abstentions":1126,"votants":1129,"blancs":10,"nuls":17,"exprimes":1102,"ratio_abstentions_inscrits":49.93,"ratio_votants_inscrits":50.07,"ratio_exprimes_votants":97.61},{"code_region":"84","libelle_region":"Auvergne-Rhône-Alpes","code_departement":"43","libelle_departement":"Haute-Loire","code_commune":"43052","libelle_commune":"Champagnac-Le-Vieux","inscrits":197,"abstentions":85,"votants":112,"blancs":1,"nuls":5,"exprimes":106,"ratio_abstentions_inscrits":43.15,"ratio_votants_inscrits":56.85,"ratio_exprimes_votants":94.64},{"code_region":"84","libelle_region":"Auvergne-Rhône-Alpes","code_departement":"43","libelle_departement":"Haute-Loire","code_commune":"43053","libelle_commune":"Champclause","inscrits":233,"abstentions":91,"votants":142,"blancs":3,"nuls":4,"exprimes":135,"ratio_abstentions_inscrits":39.06,"ratio_votants_inscrits":60.94,"ratio_exprimes_votants":95.07},{"code_region":"84","libelle_region":"Auvergne-Rhône-Alpes","code_departement":"43","libelle_departement":"Haute-Loire","code_commune":"43054","libelle_commune":"Chanaleilles","inscrits":210,"abstentions":90,"votants":120,"blancs":5,"nuls":4,"exprimes":111,"ratio_abstentions_inscrits":42.86,"ratio_votants_inscrits":57.14,"ratio_exprimes_votants":92.5},{"code_region":"84","libelle_region":"Auvergne-Rhône-Alpes","code_departement":"43","libelle_departement":"Haute-Loire","code_commune":"43055","libelle_commune":"Chaniat","inscrits":142,"abstentions":57,"votants":85,"blancs":0,"nuls":1,"exprimes":84,"ratio_abstentions_inscrits":40.14,"ratio_votants_inscrits":59.86,"ratio_exprimes_votants":98.82},{"code_region":"84","libelle_region":"Auvergne-Rhône-Alpes","code_departement":"43","libelle_departement":"Haute-Loire","code_commune":"43056","libelle_commune":"Chanteuges","inscrits":381,"abstentions":172,"votants":209,"blancs":3,"nuls":12,"exprimes":194,"ratio_abstentions_inscrits":45.14,"ratio_votants_inscrits":54.86,"ratio_exprimes_votants":92.82},{"code_region":"84","libelle_region":"Auvergne-Rhône-Alpes","code_departement":"43","libelle_departement":"Haute-Loire","code_commune":"43057","libelle_commune":"La Chapelle-Bertin","inscrits":59,"abstentions":21,"votants":38,"blancs":1,"nuls":0,"exprimes":37,"ratio_abstentions_inscrits":35.59,"ratio_votants_inscrits":64.41,"ratio_exprimes_votants":97.37},{"code_region":"84","libelle_region":"Auvergne-Rhône-Alpes","code_departement":"43","libelle_departement":"Haute-Loire","code_commune":"43058","libelle_commune":"La Chapelle-D'Aurec","inscrits":845,"abstentions":305,"votants":540,"blancs":13,"nuls":9,"exprimes":518,"ratio_abstentions_inscrits":36.09,"ratio_votants_inscrits":63.91,"ratio_exprimes_votants":95.93},{"code_region":"84","libelle_region":"Auvergne-Rhône-Alpes","code_departement":"43","libelle_departement":"Haute-Loire","code_commune":"43059","libelle_commune":"La Chapelle-Geneste","inscrits":126,"abstentions":53,"votants":73,"blancs":2,"nuls":6,"exprimes":65,"ratio_abstentions_inscrits":42.06,"ratio_votants_inscrits":57.94,"ratio_exprimes_votants":89.04},{"code_region":"84","libelle_region":"Auvergne-Rhône-Alpes","code_departement":"43","libelle_departement":"Haute-Loire","code_commune":"43060","libelle_commune":"Charraix","inscrits":68,"abstentions":26,"votants":42,"blancs":2,"nuls":0,"exprimes":40,"ratio_abstentions_inscrits":38.24,"ratio_votants_inscrits":61.76,"ratio_exprimes_votants":95.24},{"code_region":"84","libelle_region":"Auvergne-Rhône-Alpes","code_departement":"43","libelle_departement":"Haute-Loire","code_commune":"43061","libelle_commune":"Chaspinhac","inscrits":684,"abstentions":258,"votants":426,"blancs":11,"nuls":10,"exprimes":405,"ratio_abstentions_inscrits":37.72,"ratio_votants_inscrits":62.28,"ratio_exprimes_votants":95.07},{"code_region":"84","libelle_region":"Auvergne-Rhône-Alpes","code_departement":"43","libelle_departement":"Haute-Loire","code_commune":"43062","libelle_commune":"Chaspuzac","inscrits":607,"abstentions":258,"votants":349,"blancs":10,"nuls":15,"exprimes":324,"ratio_abstentions_inscrits":42.5,"ratio_votants_inscrits":57.5,"ratio_exprimes_votants":92.84},{"code_region":"84","libelle_region":"Auvergne-Rhône-Alpes","code_departement":"43","libelle_departement":"Haute-Loire","code_commune":"43063","libelle_commune":"Chassagnes","inscrits":132,"abstentions":45,"votants":87,"blancs":1,"nuls":3,"exprimes":83,"ratio_abstentions_inscrits":34.09,"ratio_votants_inscrits":65.91,"ratio_exprimes_votants":95.4},{"code_region":"84","libelle_region":"Auvergne-Rhône-Alpes","code_departement":"43","libelle_departement":"Haute-Loire","code_commune":"43064","libelle_commune":"Chassignolles","inscrits":95,"abstentions":36,"votants":59,"blancs":1,"nuls":1,"exprimes":57,"ratio_abstentions_inscrits":37.89,"ratio_votants_inscrits":62.11,"ratio_exprimes_votants":96.61},{"code_region":"84","libelle_region":"Auvergne-Rhône-Alpes","code_departement":"43","libelle_departement":"Haute-Loire","code_commune":"43065","libelle_commune":"Chastel","inscrits":133,"abstentions":55,"votants":78,"blancs":3,"nuls":0,"exprimes":75,"ratio_abstentions_inscrits":41.35,"ratio_votants_inscrits":58.65,"ratio_exprimes_votants":96.15},{"code_region":"84","libelle_region":"Auvergne-Rhône-Alpes","code_departement":"43","libelle_departement":"Haute-Loire","code_commune":"43066","libelle_commune":"Chaudeyrolles","inscrits":115,"abstentions":42,"votants":73,"blancs":1,"nuls":2,"exprimes":70,"ratio_abstentions_inscrits":36.52,"ratio_votants_inscrits":63.48,"ratio_exprimes_votants":95.89},{"code_region":"84","libelle_region":"Auvergne-Rhône-Alpes","code_departement":"43","libelle_departement":"Haute-Loire","code_commune":"43067","libelle_commune":"Chavaniac-Lafayette","inscrits":239,"abstentions":90,"votants":149,"blancs":3,"nuls":3,"exprimes":143,"ratio_abstentions_inscrits":37.66,"ratio_votants_inscrits":62.34,"ratio_exprimes_votants":95.97},{"code_region":"84","libelle_region":"Auvergne-Rhône-Alpes","code_departement":"43","libelle_departement":"Haute-Loire","code_commune":"43068","libelle_commune":"Chazelles","inscrits":40,"abstentions":11,"votants":29,"blancs":2,"nuls":0,"exprimes":27,"ratio_abstentions_inscrits":27.5,"ratio_votants_inscrits":72.5,"ratio_exprimes_votants":93.1},{"code_region":"84","libelle_region":"Auvergne-Rhône-Alpes","code_departement":"43","libelle_departement":"Haute-Loire","code_commune":"43069","libelle_commune":"Chenereilles","inscrits":275,"abstentions":113,"votants":162,"blancs":6,"nuls":4,"exprimes":152,"ratio_abstentions_inscrits":41.09,"ratio_votants_inscrits":58.91,"ratio_exprimes_votants":93.83},{"code_region":"84","libelle_region":"Auvergne-Rhône-Alpes","code_departement":"43","libelle_departement":"Haute-Loire","code_commune":"43070","libelle_commune":"Chilhac","inscrits":182,"abstentions":66,"votants":116,"blancs":12,"nuls":1,"exprimes":103,"ratio_abstentions_inscrits":36.26,"ratio_votants_inscrits":63.74,"ratio_exprimes_votants":88.79},{"code_region":"84","libelle_region":"Auvergne-Rhône-Alpes","code_departement":"43","libelle_departement":"Haute-Loire","code_commune":"43071","libelle_commune":"Chomelix","inscrits":424,"abstentions":208,"votants":216,"blancs":7,"nuls":9,"exprimes":200,"ratio_abstentions_inscrits":49.06,"ratio_votants_inscrits":50.94,"ratio_exprimes_votants":92.59},{"code_region":"84","libelle_region":"Auvergne-Rhône-Alpes","code_departement":"43","libelle_departement":"Haute-Loire","code_commune":"43072","libelle_commune":"La Chomette","inscrits":122,"abstentions":46,"votants":76,"blancs":2,"nuls":1,"exprimes":73,"ratio_abstentions_inscrits":37.7,"ratio_votants_inscrits":62.3,"ratio_exprimes_votants":96.05},{"code_region":"84","libelle_region":"Auvergne-Rhône-Alpes","code_departement":"43","libelle_departement":"Haute-Loire","code_commune":"43073","libelle_commune":"Cistrières","inscrits":158,"abstentions":63,"votants":95,"blancs":2,"nuls":2,"exprimes":91,"ratio_abstentions_inscrits":39.87,"ratio_votants_inscrits":60.13,"ratio_exprimes_votants":95.79},{"code_region":"84","libelle_region":"Auvergne-Rhône-Alpes","code_departement":"43","libelle_departement":"Haute-Loire","code_commune":"43074","libelle_commune":"Cohade","inscrits":660,"abstentions":296,"votants":364,"blancs":5,"nuls":17,"exprimes":342,"ratio_abstentions_inscrits":44.85,"ratio_votants_inscrits":55.15,"ratio_exprimes_votants":93.96},{"code_region":"84","libelle_region":"Auvergne-Rhône-Alpes","code_departement":"43","libelle_departement":"Haute-Loire","code_commune":"43075","libelle_commune":"Collat","inscrits":87,"abstentions":24,"votants":63,"blancs":0,"nuls":4,"exprimes":59,"ratio_abstentions_inscrits":27.59,"ratio_votants_inscrits":72.41,"ratio_exprimes_votants":93.65},{"code_region":"84","libelle_region":"Auvergne-Rhône-Alpes","code_departement":"43","libelle_departement":"Haute-Loire","code_commune":"43076","libelle_commune":"Connangles","inscrits":125,"abstentions":47,"votants":78,"blancs":1,"nuls":0,"exprimes":77,"ratio_abstentions_inscrits":37.6,"ratio_votants_inscrits":62.4,"ratio_exprimes_votants":98.72},{"code_region":"84","libelle_region":"Auvergne-Rhône-Alpes","code_departement":"43","libelle_departement":"Haute-Loire","code_commune":"43077","libelle_commune":"Costaros","inscrits":425,"abstentions":165,"votants":260,"blancs":6,"nuls":7,"exprimes":247,"ratio_abstentions_inscrits":38.82,"ratio_votants_inscrits":61.18,"ratio_exprimes_votants":95.0},{"code_region":"84","libelle_region":"Auvergne-Rhône-Alpes","code_departement":"43","libelle_departement":"Haute-Loire","code_commune":"43078","libelle_commune":"Coubon","inscrits":2631,"abstentions":1046,"votants":1585,"blancs":36,"nuls":32,"exprimes":1517,"ratio_abstentions_inscrits":39.76,"ratio_votants_inscrits":60.24,"ratio_exprimes_votants":95.71},{"code_region":"84","libelle_region":"Auvergne-Rhône-Alpes","code_departement":"43","libelle_departement":"Haute-Loire","code_commune":"43079","libelle_commune":"Couteuges","inscrits":192,"abstentions":76,"votants":116,"blancs":1,"nuls":7,"exprimes":108,"ratio_abstentions_inscrits":39.58,"ratio_votants_inscrits":60.42,"ratio_exprimes_votants":93.1},{"code_region":"84","libelle_region":"Auvergne-Rhône-Alpes","code_departement":"43","libelle_departement":"Haute-Loire","code_commune":"43080","libelle_commune":"Craponne-Sur-Arzon","inscrits":1529,"abstentions":708,"votants":821,"blancs":12,"nuls":14,"exprimes":795,"ratio_abstentions_inscrits":46.3,"ratio_votants_inscrits":53.7,"ratio_exprimes_votants":96.83},{"code_region":"84","libelle_region":"Auvergne-Rhône-Alpes","code_departement":"43","libelle_departement":"Haute-Loire","code_commune":"43082","libelle_commune":"Cronce","inscrits":79,"abstentions":45,"votants":34,"blancs":0,"nuls":0,"exprimes":34,"ratio_abstentions_inscrits":56.96,"ratio_votants_inscrits":43.04,"ratio_exprimes_votants":100.0},{"code_region":"84","libelle_region":"Auvergne-Rhône-Alpes","code_departement":"43","libelle_departement":"Haute-Loire","code_commune":"43083","libelle_commune":"Cubelles","inscrits":124,"abstentions":58,"votants":66,"blancs":1,"nuls":2,"exprimes":63,"ratio_abstentions_inscrits":46.77,"ratio_votants_inscrits":53.23,"ratio_exprimes_votants":95.45},{"code_region":"84","libelle_region":"Auvergne-Rhône-Alpes","code_departement":"43","libelle_departement":"Haute-Loire","code_commune":"43084","libelle_commune":"Cussac-Sur-Loire","inscrits":1392,"abstentions":526,"votants":866,"blancs":17,"nuls":19,"exprimes":830,"ratio_abstentions_inscrits":37.79,"ratio_votants_inscrits":62.21,"ratio_exprimes_votants":95.84},{"code_region":"84","libelle_region":"Auvergne-Rhône-Alpes","code_departement":"43","libelle_departement":"Haute-Loire","code_commune":"43085","libelle_commune":"Desges","inscrits":55,"abstentions":22,"votants":33,"blancs":4,"nuls":0,"exprimes":29,"ratio_abstentions_inscrits":40.0,"ratio_votants_inscrits":60.0,"ratio_exprimes_votants":87.88},{"code_region":"84","libelle_region":"Auvergne-Rhône-Alpes","code_departement":"43","libelle_departement":"Haute-Loire","code_commune":"43086","libelle_commune":"Domeyrat","inscrits":159,"abstentions":52,"votants":107,"blancs":1,"nuls":3,"exprimes":103,"ratio_abstentions_inscrits":32.7,"ratio_votants_inscrits":67.3,"ratio_exprimes_votants":96.26},{"code_region":"84","libelle_region":"Auvergne-Rhône-Alpes","code_departement":"43","libelle_departement":"Haute-Loire","code_commune":"43087","libelle_commune":"Dunières","inscrits":2063,"abstentions":896,"votants":1167,"blancs":30,"nuls":24,"exprimes":1113,"ratio_abstentions_inscrits":43.43,"ratio_votants_inscrits":56.57,"ratio_exprimes_votants":95.37},{"code_region":"84","libelle_region":"Auvergne-Rhône-Alpes","code_departement":"43","libelle_departement":"Haute-Loire","code_commune":"43088","libelle_commune":"Espalem","inscrits":287,"abstentions":124,"votants":163,"blancs":7,"nuls":2,"exprimes":154,"ratio_abstentions_inscrits":43.21,"ratio_votants_inscrits":56.79,"ratio_exprimes_votants":94.48},{"code_region":"84","libelle_region":"Auvergne-Rhône-Alpes","code_departement":"43","libelle_departement":"Haute-Loire","code_commune":"43089","libelle_commune":"Espaly-Saint-Marcel","inscrits":2502,"abstentions":1112,"votants":1390,"blancs":25,"nuls":18,"exprimes":1347,"ratio_abstentions_inscrits":44.44,"ratio_votants_inscrits":55.56,"ratio_exprimes_votants":96.91},{"code_region":"84","libelle_region":"Auvergne-Rhône-Alpes","code_departement":"43","libelle_departement":"Haute-Loire","code_commune":"43090","libelle_commune":"Esplantas-Vazeilles","inscrits":126,"abstentions":43,"votants":83,"blancs":3,"nuls":1,"exprimes":79,"ratio_abstentions_inscrits":34.13,"ratio_votants_inscrits":65.87,"ratio_exprimes_votants":95.18},{"code_region":"84","libelle_region":"Auvergne-Rhône-Alpes","code_departement":"43","libelle_departement":"Haute-Loire","code_commune":"43091","libelle_commune":"Les Estables","inscrits":319,"abstentions":108,"votants":211,"blancs":2,"nuls":7,"exprimes":202,"ratio_abstentions_inscrits":33.86,"ratio_votants_inscrits":66.14,"ratio_exprimes_votants":95.73},{"code_region":"84","libelle_region":"Auvergne-Rhône-Alpes","code_departement":"43","libelle_departement":"Haute-Loire","code_commune":"43092","libelle_commune":"Fay-Sur-Lignon","inscrits":287,"abstentions":119,"votants":168,"blancs":3,"nuls":2,"exprimes":163,"ratio_abstentions_inscrits":41.46,"ratio_votants_inscrits":58.54,"ratio_exprimes_votants":97.02},{"code_region":"84","libelle_region":"Auvergne-Rhône-Alpes","code_departement":"43","libelle_departement":"Haute-Loire","code_commune":"43093","libelle_commune":"Félines","inscrits":297,"abstentions":116,"votants":181,"blancs":9,"nuls":6,"exprimes":166,"ratio_abstentions_inscrits":39.06,"ratio_votants_inscrits":60.94,"ratio_exprimes_votants":91.71},{"code_region":"84","libelle_region":"Auvergne-Rhône-Alpes","code_departement":"43","libelle_departement":"Haute-Loire","code_commune":"43094","libelle_commune":"Ferrussac","inscrits":79,"abstentions":31,"votants":48,"blancs":0,"nuls":3,"exprimes":45,"ratio_abstentions_inscrits":39.24,"ratio_votants_inscrits":60.76,"ratio_exprimes_votants":93.75},{"code_region":"84","libelle_region":"Auvergne-Rhône-Alpes","code_departement":"43","libelle_departement":"Haute-Loire","code_commune":"43095","libelle_commune":"Fix-Saint-Geneys","inscrits":128,"abstentions":49,"votants":79,"blancs":0,"nuls":1,"exprimes":78,"ratio_abstentions_inscrits":38.28,"ratio_votants_inscrits":61.72,"ratio_exprimes_votants":98.73},{"code_region":"84","libelle_region":"Auvergne-Rhône-Alpes","code_departement":"43","libelle_departement":"Haute-Loire","code_commune":"43096","libelle_commune":"Fontannes","inscrits":638,"abstentions":252,"votants":386,"blancs":9,"nuls":9,"exprimes":368,"ratio_abstentions_inscrits":39.5,"ratio_votants_inscrits":60.5,"ratio_exprimes_votants":95.34},{"code_region":"84","libelle_region":"Auvergne-Rhône-Alpes","code_departement":"43","libelle_departement":"Haute-Loire","code_commune":"43097","libelle_commune":"Freycenet-La-Cuche","inscrits":137,"abstentions":43,"votants":94,"blancs":1,"nuls":2,"exprimes":91,"ratio_abstentions_inscrits":31.39,"ratio_votants_inscrits":68.61,"ratio_exprimes_votants":96.81},{"code_region":"84","libelle_region":"Auvergne-Rhône-Alpes","code_departement":"43","libelle_departement":"Haute-Loire","code_commune":"43098","libelle_commune":"Freycenet-La-Tour","inscrits":117,"abstentions":48,"votants":69,"blancs":0,"nuls":0,"exprimes":69,"ratio_abstentions_inscrits":41.03,"ratio_votants_inscrits":58.97,"ratio_exprimes_votants":100.0},{"code_region":"84","libelle_region":"Auvergne-Rhône-Alpes","code_departement":"43","libelle_departement":"Haute-Loire","code_commune":"43099","libelle_commune":"Frugerès-Les-Mines","inscrits":360,"abstentions":161,"votants":199,"blancs":2,"nuls":5,"exprimes":192,"ratio_abstentions_inscrits":44.72,"ratio_votants_inscrits":55.28,"ratio_exprimes_votants":96.48},{"code_region":"84","libelle_region":"Auvergne-Rhône-Alpes","code_departement":"43","libelle_departement":"Haute-Loire","code_commune":"43100","libelle_commune":"Frugières-Le-Pin","inscrits":162,"abstentions":68,"votants":94,"blancs":0,"nuls":0,"exprimes":94,"ratio_abstentions_inscrits":41.98,"ratio_votants_inscrits":58.02,"ratio_exprimes_votants":100.0},{"code_region":"84","libelle_region":"Auvergne-Rhône-Alpes","code_departement":"43","libelle_departement":"Haute-Loire","code_commune":"43101","libelle_commune":"Goudet","inscrits":108,"abstentions":33,"votants":75,"blancs":4,"nuls":1,"exprimes":70,"ratio_abstentions_inscrits":30.56,"ratio_votants_inscrits":69.44,"ratio_exprimes_votants":93.33},{"code_region":"84","libelle_region":"Auvergne-Rhône-Alpes","code_departement":"43","libelle_departement":"Haute-Loire","code_commune":"43102","libelle_commune":"Grazac","inscrits":929,"abstentions":349,"votants":580,"blancs":9,"nuls":7,"exprimes":564,"ratio_abstentions_inscrits":37.57,"ratio_votants_inscrits":62.43,"ratio_exprimes_votants":97.24},{"code_region":"84","libelle_region":"Auvergne-Rhône-Alpes","code_departement":"43","libelle_departement":"Haute-Loire","code_commune":"43103","libelle_commune":"Grenier-Montgon","inscrits":124,"abstentions":46,"votants":78,"blancs":1,"nuls":3,"exprimes":74,"ratio_abstentions_inscrits":37.1,"ratio_votants_inscrits":62.9,"ratio_exprimes_votants":94.87},{"code_region":"84","libelle_region":"Auvergne-Rhône-Alpes","code_departement":"43","libelle_departement":"Haute-Loire","code_commune":"43104","libelle_commune":"Grèzes","inscrits":198,"abstentions":76,"votants":122,"blancs":3,"nuls":5,"exprimes":114,"ratio_abstentions_inscrits":38.38,"ratio_votants_inscrits":61.62,"ratio_exprimes_votants":93.44},{"code_region":"84","libelle_region":"Auvergne-Rhône-Alpes","code_departement":"43","libelle_departement":"Haute-Loire","code_commune":"43105","libelle_commune":"Javaugues","inscrits":169,"abstentions":58,"votants":111,"blancs":1,"nuls":5,"exprimes":105,"ratio_abstentions_inscrits":34.32,"ratio_votants_inscrits":65.68,"ratio_exprimes_votants":94.59},{"code_region":"84","libelle_region":"Auvergne-Rhône-Alpes","code_departement":"43","libelle_departement":"Haute-Loire","code_commune":"43106","libelle_commune":"Jax","inscrits":137,"abstentions":46,"votants":91,"blancs":4,"nuls":4,"exprimes":83,"ratio_abstentions_inscrits":33.58,"ratio_votants_inscrits":66.42,"ratio_exprimes_votants":91.21},{"code_region":"84","libelle_region":"Auvergne-Rhône-Alpes","code_departement":"43","libelle_departement":"Haute-Loire","code_commune":"43107","libelle_commune":"Josat","inscrits":93,"abstentions":44,"votants":49,"blancs":0,"nuls":1,"exprimes":48,"ratio_abstentions_inscrits":47.31,"ratio_votants_inscrits":52.69,"ratio_exprimes_votants":97.96},{"code_region":"84","libelle_region":"Auvergne-Rhône-Alpes","code_departement":"43","libelle_departement":"Haute-Loire","code_commune":"43108","libelle_commune":"Jullianges","inscrits":387,"abstentions":161,"votants":226,"blancs":10,"nuls":13,"exprimes":203,"ratio_abstentions_inscrits":41.6,"ratio_votants_inscrits":58.4,"ratio_exprimes_votants":89.82},{"code_region":"84","libelle_region":"Auvergne-Rhône-Alpes","code_departement":"43","libelle_departement":"Haute-Loire","code_commune":"43109","libelle_commune":"Lafarre","inscrits":80,"abstentions":33,"votants":47,"blancs":1,"nuls":2,"exprimes":44,"ratio_abstentions_inscrits":41.25,"ratio_votants_inscrits":58.75,"ratio_exprimes_votants":93.62},{"code_region":"84","libelle_region":"Auvergne-Rhône-Alpes","code_departement":"43","libelle_departement":"Haute-Loire","code_commune":"43110","libelle_commune":"Lamothe","inscrits":669,"abstentions":285,"votants":384,"blancs":7,"nuls":13,"exprimes":364,"ratio_abstentions_inscrits":42.6,"ratio_votants_inscrits":57.4,"ratio_exprimes_votants":94.79},{"code_region":"84","libelle_region":"Auvergne-Rhône-Alpes","code_departement":"43","libelle_departement":"Haute-Loire","code_commune":"43111","libelle_commune":"Landos","inscrits":702,"abstentions":292,"votants":410,"blancs":4,"nuls":8,"exprimes":398,"ratio_abstentions_inscrits":41.6,"ratio_votants_inscrits":58.4,"ratio_exprimes_votants":97.07},{"code_region":"84","libelle_region":"Auvergne-Rhône-Alpes","code_departement":"43","libelle_departement":"Haute-Loire","code_commune":"43112","libelle_commune":"Langeac","inscrits":2777,"abstentions":1338,"votants":1439,"blancs":25,"nuls":27,"exprimes":1387,"ratio_abstentions_inscrits":48.18,"ratio_votants_inscrits":51.82,"ratio_exprimes_votants":96.39},{"code_region":"84","libelle_region":"Auvergne-Rhône-Alpes","code_departement":"43","libelle_departement":"Haute-Loire","code_commune":"43113","libelle_commune":"Lantriac","inscrits":1591,"abstentions":696,"votants":895,"blancs":17,"nuls":14,"exprimes":864,"ratio_abstentions_inscrits":43.75,"ratio_votants_inscrits":56.25,"ratio_exprimes_votants":96.54},{"code_region":"84","libelle_region":"Auvergne-Rhône-Alpes","code_departement":"43","libelle_departement":"Haute-Loire","code_commune":"43114","libelle_commune":"Lapte","inscrits":1498,"abstentions":693,"votants":805,"blancs":24,"nuls":18,"exprimes":763,"ratio_abstentions_inscrits":46.26,"ratio_votants_inscrits":53.74,"ratio_exprimes_votants":94.78},{"code_region":"84","libelle_region":"Auvergne-Rhône-Alpes","code_departement":"43","libelle_departement":"Haute-Loire","code_commune":"43115","libelle_commune":"Laussonne","inscrits":854,"abstentions":347,"votants":507,"blancs":11,"nuls":9,"exprimes":487,"ratio_abstentions_inscrits":40.63,"ratio_votants_inscrits":59.37,"ratio_exprimes_votants":96.06},{"code_region":"84","libelle_region":"Auvergne-Rhône-Alpes","code_departement":"43","libelle_departement":"Haute-Loire","code_commune":"43116","libelle_commune":"Laval-Sur-Doulon","inscrits":57,"abstentions":22,"votants":35,"blancs":1,"nuls":0,"exprimes":34,"ratio_abstentions_inscrits":38.6,"ratio_votants_inscrits":61.4,"ratio_exprimes_votants":97.14},{"code_region":"84","libelle_region":"Auvergne-Rhône-Alpes","code_departement":"43","libelle_departement":"Haute-Loire","code_commune":"43117","libelle_commune":"Lavaudieu","inscrits":242,"abstentions":105,"votants":137,"blancs":3,"nuls":2,"exprimes":132,"ratio_abstentions_inscrits":43.39,"ratio_votants_inscrits":56.61,"ratio_exprimes_votants":96.35},{"code_region":"84","libelle_region":"Auvergne-Rhône-Alpes","code_departement":"43","libelle_departement":"Haute-Loire","code_commune":"43118","libelle_commune":"Lavoûte-Chilhac","inscrits":265,"abstentions":120,"votants":145,"blancs":2,"nuls":0,"exprimes":143,"ratio_abstentions_inscrits":45.28,"ratio_votants_inscrits":54.72,"ratio_exprimes_votants":98.62},{"code_region":"84","libelle_region":"Auvergne-Rhône-Alpes","code_departement":"43","libelle_departement":"Haute-Loire","code_commune":"43119","libelle_commune":"Lavoûte-Sur-Loire","inscrits":554,"abstentions":228,"votants":326,"blancs":8,"nuls":7,"exprimes":311,"ratio_abstentions_inscrits":41.16,"ratio_votants_inscrits":58.84,"ratio_exprimes_votants":95.4},{"code_region":"84","libelle_region":"Auvergne-Rhône-Alpes","code_departement":"43","libelle_departement":"Haute-Loire","code_commune":"43120","libelle_commune":"Lempdes-Sur-Allagnon","inscrits":993,"abstentions":499,"votants":494,"blancs":15,"nuls":9,"exprimes":470,"ratio_abstentions_inscrits":50.25,"ratio_votants_inscrits":49.75,"ratio_exprimes_votants":95.14},{"code_region":"84","libelle_region":"Auvergne-Rhône-Alpes","code_departement":"43","libelle_departement":"Haute-Loire","code_commune":"43121","libelle_commune":"Léotoing","inscrits":186,"abstentions":70,"votants":116,"blancs":2,"nuls":4,"exprimes":110,"ratio_abstentions_inscrits":37.63,"ratio_votants_inscrits":62.37,"ratio_exprimes_votants":94.83},{"code_region":"84","libelle_region":"Auvergne-Rhône-Alpes","code_departement":"43","libelle_departement":"Haute-Loire","code_commune":"43122","libelle_commune":"Lissac","inscrits":251,"abstentions":110,"votants":141,"blancs":4,"nuls":3,"exprimes":134,"ratio_abstentions_inscrits":43.82,"ratio_votants_inscrits":56.18,"ratio_exprimes_votants":95.04},{"code_region":"84","libelle_region":"Auvergne-Rhône-Alpes","code_departement":"43","libelle_departement":"Haute-Loire","code_commune":"43123","libelle_commune":"Lorlanges","inscrits":285,"abstentions":74,"votants":211,"blancs":3,"nuls":7,"exprimes":201,"ratio_abstentions_inscrits":25.96,"ratio_votants_inscrits":74.04,"ratio_exprimes_votants":95.26},{"code_region":"84","libelle_region":"Auvergne-Rhône-Alpes","code_departement":"43","libelle_departement":"Haute-Loire","code_commune":"43124","libelle_commune":"Loudes","inscrits":783,"abstentions":364,"votants":419,"blancs":7,"nuls":13,"exprimes":399,"ratio_abstentions_inscrits":46.49,"ratio_votants_inscrits":53.51,"ratio_exprimes_votants":95.23},{"code_region":"84","libelle_region":"Auvergne-Rhône-Alpes","code_departement":"43","libelle_departement":"Haute-Loire","code_commune":"43125","libelle_commune":"Lubilhac","inscrits":120,"abstentions":45,"votants":75,"blancs":4,"nuls":6,"exprimes":65,"ratio_abstentions_inscrits":37.5,"ratio_votants_inscrits":62.5,"ratio_exprimes_votants":86.67},{"code_region":"84","libelle_region":"Auvergne-Rhône-Alpes","code_departement":"43","libelle_departement":"Haute-Loire","code_commune":"43126","libelle_commune":"Malrevers","inscrits":626,"abstentions":275,"votants":351,"blancs":3,"nuls":6,"exprimes":342,"ratio_abstentions_inscrits":43.93,"ratio_votants_inscrits":56.07,"ratio_exprimes_votants":97.44},{"code_region":"84","libelle_region":"Auvergne-Rhône-Alpes","code_departement":"43","libelle_departement":"Haute-Loire","code_commune":"43127","libelle_commune":"Malvalette","inscrits":680,"abstentions":309,"votants":371,"blancs":8,"nuls":7,"exprimes":356,"ratio_abstentions_inscrits":45.44,"ratio_votants_inscrits":54.56,"ratio_exprimes_votants":95.96},{"code_region":"84","libelle_region":"Auvergne-Rhône-Alpes","code_departement":"43","libelle_departement":"Haute-Loire","code_commune":"43128","libelle_commune":"Malvières","inscrits":117,"abstentions":34,"votants":83,"blancs":3,"nuls":3,"exprimes":77,"ratio_abstentions_inscrits":29.06,"ratio_votants_inscrits":70.94,"ratio_exprimes_votants":92.77},{"code_region":"84","libelle_region":"Auvergne-Rhône-Alpes","code_departement":"43","libelle_departement":"Haute-Loire","code_commune":"43129","libelle_commune":"Le Mas-De-Tence","inscrits":187,"abstentions":51,"votants":136,"blancs":4,"nuls":0,"exprimes":132,"ratio_abstentions_inscrits":27.27,"ratio_votants_inscrits":72.73,"ratio_exprimes_votants":97.06},{"code_region":"84","libelle_region":"Auvergne-Rhône-Alpes","code_departement":"43","libelle_departement":"Haute-Loire","code_commune":"43130","libelle_commune":"Mazet-Saint-Voy","inscrits":969,"abstentions":444,"votants":525,"blancs":15,"nuls":13,"exprimes":497,"ratio_abstentions_inscrits":45.82,"ratio_votants_inscrits":54.18,"ratio_exprimes_votants":94.67},{"code_region":"84","libelle_region":"Auvergne-Rhône-Alpes","code_departement":"43","libelle_departement":"Haute-Loire","code_commune":"43131","libelle_commune":"Mazerat-Aurouze","inscrits":172,"abstentions":64,"votants":108,"blancs":1,"nuls":3,"exprimes":104,"ratio_abstentions_inscrits":37.21,"ratio_votants_inscrits":62.79,"ratio_exprimes_votants":96.3},{"code_region":"84","libelle_region":"Auvergne-Rhône-Alpes","code_departement":"43","libelle_departement":"Haute-Loire","code_commune":"43132","libelle_commune":"Mazeyrat-D'Allier","inscrits":1266,"abstentions":614,"votants":652,"blancs":9,"nuls":17,"exprimes":626,"ratio_abstentions_inscrits":48.5,"ratio_votants_inscrits":51.5,"ratio_exprimes_votants":96.01},{"code_region":"84","libelle_region":"Auvergne-Rhône-Alpes","code_departement":"43","libelle_departement":"Haute-Loire","code_commune":"43133","libelle_commune":"Mercoeur","inscrits":143,"abstentions":61,"votants":82,"blancs":2,"nuls":3,"exprimes":77,"ratio_abstentions_inscrits":42.66,"ratio_votants_inscrits":57.34,"ratio_exprimes_votants":93.9},{"code_region":"84","libelle_region":"Auvergne-Rhône-Alpes","code_departement":"43","libelle_departement":"Haute-Loire","code_commune":"43134","libelle_commune":"Mézères","inscrits":172,"abstentions":54,"votants":118,"blancs":2,"nuls":0,"exprimes":116,"ratio_abstentions_inscrits":31.4,"ratio_votants_inscrits":68.6,"ratio_exprimes_votants":98.31},{"code_region":"84","libelle_region":"Auvergne-Rhône-Alpes","code_departement":"43","libelle_departement":"Haute-Loire","code_commune":"43135","libelle_commune":"Le Monastier-Sur-Gazeille","inscrits":1337,"abstentions":540,"votants":797,"blancs":16,"nuls":13,"exprimes":768,"ratio_abstentions_inscrits":40.39,"ratio_votants_inscrits":59.61,"ratio_exprimes_votants":96.36},{"code_region":"84","libelle_region":"Auvergne-Rhône-Alpes","code_departement":"43","libelle_departement":"Haute-Loire","code_commune":"43136","libelle_commune":"Monistrol-D'Allier","inscrits":212,"abstentions":75,"votants":137,"blancs":5,"nuls":6,"exprimes":126,"ratio_abstentions_inscrits":35.38,"ratio_votants_inscrits":64.62,"ratio_exprimes_votants":91.97},{"code_region":"84","libelle_region":"Auvergne-Rhône-Alpes","code_departement":"43","libelle_departement":"Haute-Loire","code_commune":"43137","libelle_commune":"Monistrol-Sur-Loire","inscrits":7244,"abstentions":3182,"votants":4062,"blancs":61,"nuls":54,"exprimes":3947,"ratio_abstentions_inscrits":43.93,"ratio_votants_inscrits":56.07,"ratio_exprimes_votants":97.17},{"code_region":"84","libelle_region":"Auvergne-Rhône-Alpes","code_departement":"43","libelle_departement":"Haute-Loire","code_commune":"43138","libelle_commune":"Monlet","inscrits":360,"abstentions":171,"votants":189,"blancs":5,"nuls":4,"exprimes":180,"ratio_abstentions_inscrits":47.5,"ratio_votants_inscrits":52.5,"ratio_exprimes_votants":95.24},{"code_region":"84","libelle_region":"Auvergne-Rhône-Alpes","code_departement":"43","libelle_departement":"Haute-Loire","code_commune":"43139","libelle_commune":"Montclard","inscrits":41,"abstentions":17,"votants":24,"blancs":0,"nuls":0,"exprimes":24,"ratio_abstentions_inscrits":41.46,"ratio_votants_inscrits":58.54,"ratio_exprimes_votants":100.0},{"code_region":"84","libelle_region":"Auvergne-Rhône-Alpes","code_departement":"43","libelle_departement":"Haute-Loire","code_commune":"43140","libelle_commune":"Le Monteil","inscrits":560,"abstentions":229,"votants":331,"blancs":12,"nuls":8,"exprimes":311,"ratio_abstentions_inscrits":40.89,"ratio_votants_inscrits":59.11,"ratio_exprimes_votants":93.96},{"code_region":"84","libelle_region":"Auvergne-Rhône-Alpes","code_departement":"43","libelle_departement":"Haute-Loire","code_commune":"43141","libelle_commune":"Montfaucon-En-Velay","inscrits":923,"abstentions":405,"votants":518,"blancs":12,"nuls":4,"exprimes":502,"ratio_abstentions_inscrits":43.88,"ratio_votants_inscrits":56.12,"ratio_exprimes_votants":96.91},{"code_region":"84","libelle_region":"Auvergne-Rhône-Alpes","code_departement":"43","libelle_departement":"Haute-Loire","code_commune":"43142","libelle_commune":"Montregard","inscrits":491,"abstentions":214,"votants":277,"blancs":9,"nuls":15,"exprimes":253,"ratio_abstentions_inscrits":43.58,"ratio_votants_inscrits":56.42,"ratio_exprimes_votants":91.34},{"code_region":"84","libelle_region":"Auvergne-Rhône-Alpes","code_departement":"43","libelle_departement":"Haute-Loire","code_commune":"43143","libelle_commune":"Montusclat","inscrits":142,"abstentions":56,"votants":86,"blancs":4,"nuls":1,"exprimes":81,"ratio_abstentions_inscrits":39.44,"ratio_votants_inscrits":60.56,"ratio_exprimes_votants":94.19},{"code_region":"84","libelle_region":"Auvergne-Rhône-Alpes","code_departement":"43","libelle_departement":"Haute-Loire","code_commune":"43144","libelle_commune":"Moudeyres","inscrits":102,"abstentions":46,"votants":56,"blancs":3,"nuls":2,"exprimes":51,"ratio_abstentions_inscrits":45.1,"ratio_votants_inscrits":54.9,"ratio_exprimes_votants":91.07},{"code_region":"84","libelle_region":"Auvergne-Rhône-Alpes","code_departement":"43","libelle_departement":"Haute-Loire","code_commune":"43145","libelle_commune":"Ouides","inscrits":58,"abstentions":16,"votants":42,"blancs":1,"nuls":1,"exprimes":40,"ratio_abstentions_inscrits":27.59,"ratio_votants_inscrits":72.41,"ratio_exprimes_votants":95.24},{"code_region":"84","libelle_region":"Auvergne-Rhône-Alpes","code_departement":"43","libelle_departement":"Haute-Loire","code_commune":"43147","libelle_commune":"Paulhac","inscrits":544,"abstentions":237,"votants":307,"blancs":7,"nuls":7,"exprimes":293,"ratio_abstentions_inscrits":43.57,"ratio_votants_inscrits":56.43,"ratio_exprimes_votants":95.44},{"code_region":"84","libelle_region":"Auvergne-Rhône-Alpes","code_departement":"43","libelle_departement":"Haute-Loire","code_commune":"43148","libelle_commune":"Paulhaguet","inscrits":595,"abstentions":284,"votants":311,"blancs":11,"nuls":11,"exprimes":289,"ratio_abstentions_inscrits":47.73,"ratio_votants_inscrits":52.27,"ratio_exprimes_votants":92.93},{"code_region":"84","libelle_region":"Auvergne-Rhône-Alpes","code_departement":"43","libelle_departement":"Haute-Loire","code_commune":"43149","libelle_commune":"Pébrac","inscrits":108,"abstentions":36,"votants":72,"blancs":2,"nuls":3,"exprimes":67,"ratio_abstentions_inscrits":33.33,"ratio_votants_inscrits":66.67,"ratio_exprimes_votants":93.06},{"code_region":"84","libelle_region":"Auvergne-Rhône-Alpes","code_departement":"43","libelle_departement":"Haute-Loire","code_commune":"43150","libelle_commune":"Le Pertuis","inscrits":463,"abstentions":148,"votants":315,"blancs":11,"nuls":7,"exprimes":297,"ratio_abstentions_inscrits":31.97,"ratio_votants_inscrits":68.03,"ratio_exprimes_votants":94.29},{"code_region":"84","libelle_region":"Auvergne-Rhône-Alpes","code_departement":"43","libelle_departement":"Haute-Loire","code_commune":"43151","libelle_commune":"Pinols","inscrits":210,"abstentions":89,"votants":121,"blancs":3,"nuls":10,"exprimes":108,"ratio_abstentions_inscrits":42.38,"ratio_votants_inscrits":57.62,"ratio_exprimes_votants":89.26},{"code_region":"84","libelle_region":"Auvergne-Rhône-Alpes","code_departement":"43","libelle_departement":"Haute-Loire","code_commune":"43152","libelle_commune":"Polignac","inscrits":2388,"abstentions":979,"votants":1409,"blancs":20,"nuls":24,"exprimes":1365,"ratio_abstentions_inscrits":41.0,"ratio_votants_inscrits":59.0,"ratio_exprimes_votants":96.88},{"code_region":"84","libelle_region":"Auvergne-Rhône-Alpes","code_departement":"43","libelle_departement":"Haute-Loire","code_commune":"43153","libelle_commune":"Pont-Salomon","inscrits":1324,"abstentions":556,"votants":768,"blancs":9,"nuls":11,"exprimes":748,"ratio_abstentions_inscrits":41.99,"ratio_votants_inscrits":58.01,"ratio_exprimes_votants":97.4},{"code_region":"84","libelle_region":"Auvergne-Rhône-Alpes","code_departement":"43","libelle_departement":"Haute-Loire","code_commune":"43154","libelle_commune":"Pradelles","inscrits":372,"abstentions":156,"votants":216,"blancs":8,"nuls":8,"exprimes":200,"ratio_abstentions_inscrits":41.94,"ratio_votants_inscrits":58.06,"ratio_exprimes_votants":92.59},{"code_region":"84","libelle_region":"Auvergne-Rhône-Alpes","code_departement":"43","libelle_departement":"Haute-Loire","code_commune":"43155","libelle_commune":"Prades","inscrits":96,"abstentions":33,"votants":63,"blancs":2,"nuls":1,"exprimes":60,"ratio_abstentions_inscrits":34.38,"ratio_votants_inscrits":65.62,"ratio_exprimes_votants":95.24},{"code_region":"84","libelle_region":"Auvergne-Rhône-Alpes","code_departement":"43","libelle_departement":"Haute-Loire","code_commune":"43156","libelle_commune":"Présailles","inscrits":149,"abstentions":77,"votants":72,"blancs":1,"nuls":0,"exprimes":71,"ratio_abstentions_inscrits":51.68,"ratio_votants_inscrits":48.32,"ratio_exprimes_votants":98.61},{"code_region":"84","libelle_region":"Auvergne-Rhône-Alpes","code_departement":"43","libelle_departement":"Haute-Loire","code_commune":"43157","libelle_commune":"Le Puy-En-Velay","inscrits":12330,"abstentions":6144,"votants":6186,"blancs":76,"nuls":104,"exprimes":6006,"ratio_abstentions_inscrits":49.83,"ratio_votants_inscrits":50.17,"ratio_exprimes_votants":97.09},{"code_region":"84","libelle_region":"Auvergne-Rhône-Alpes","code_departement":"43","libelle_departement":"Haute-Loire","code_commune":"43158","libelle_commune":"Queyrières","inscrits":327,"abstentions":106,"votants":221,"blancs":3,"nuls":5,"exprimes":213,"ratio_abstentions_inscrits":32.42,"ratio_votants_inscrits":67.58,"ratio_exprimes_votants":96.38},{"code_region":"84","libelle_region":"Auvergne-Rhône-Alpes","code_departement":"43","libelle_departement":"Haute-Loire","code_commune":"43159","libelle_commune":"Raucoules","inscrits":755,"abstentions":280,"votants":475,"blancs":11,"nuls":8,"exprimes":456,"ratio_abstentions_inscrits":37.09,"ratio_votants_inscrits":62.91,"ratio_exprimes_votants":96.0},{"code_region":"84","libelle_region":"Auvergne-Rhône-Alpes","code_departement":"43","libelle_departement":"Haute-Loire","code_commune":"43160","libelle_commune":"Rauret","inscrits":183,"abstentions":54,"votants":129,"blancs":1,"nuls":0,"exprimes":128,"ratio_abstentions_inscrits":29.51,"ratio_votants_inscrits":70.49,"ratio_exprimes_votants":99.22},{"code_region":"84","libelle_region":"Auvergne-Rhône-Alpes","code_departement":"43","libelle_departement":"Haute-Loire","code_commune":"43162","libelle_commune":"Retournac","inscrits":2399,"abstentions":947,"votants":1452,"blancs":14,"nuls":31,"exprimes":1407,"ratio_abstentions_inscrits":39.47,"ratio_votants_inscrits":60.53,"ratio_exprimes_votants":96.9},{"code_region":"84","libelle_region":"Auvergne-Rhône-Alpes","code_departement":"43","libelle_departement":"Haute-Loire","code_commune":"43163","libelle_commune":"Riotord","inscrits":971,"abstentions":371,"votants":600,"blancs":14,"nuls":7,"exprimes":579,"ratio_abstentions_inscrits":38.21,"ratio_votants_inscrits":61.79,"ratio_exprimes_votants":96.5},{"code_region":"84","libelle_region":"Auvergne-Rhône-Alpes","code_departement":"43","libelle_departement":"Haute-Loire","code_commune":"43164","libelle_commune":"Roche-En-Régnier","inscrits":477,"abstentions":172,"votants":305,"blancs":11,"nuls":11,"exprimes":283,"ratio_abstentions_inscrits":36.06,"ratio_votants_inscrits":63.94,"ratio_exprimes_votants":92.79},{"code_region":"84","libelle_region":"Auvergne-Rhône-Alpes","code_departement":"43","libelle_departement":"Haute-Loire","code_commune":"43165","libelle_commune":"Rosières","inscrits":1204,"abstentions":504,"votants":700,"blancs":13,"nuls":15,"exprimes":672,"ratio_abstentions_inscrits":41.86,"ratio_votants_inscrits":58.14,"ratio_exprimes_votants":96.0},{"code_region":"84","libelle_region":"Auvergne-Rhône-Alpes","code_departement":"43","libelle_departement":"Haute-Loire","code_commune":"43166","libelle_commune":"Saint-André-De-Chalencon","inscrits":322,"abstentions":103,"votants":219,"blancs":2,"nuls":4,"exprimes":213,"ratio_abstentions_inscrits":31.99,"ratio_votants_inscrits":68.01,"ratio_exprimes_votants":97.26},{"code_region":"84","libelle_region":"Auvergne-Rhône-Alpes","code_departement":"43","libelle_departement":"Haute-Loire","code_commune":"43167","libelle_commune":"Saint-Arcons-D'Allier","inscrits":183,"abstentions":68,"votants":115,"blancs":0,"nuls":0,"exprimes":115,"ratio_abstentions_inscrits":37.16,"ratio_votants_inscrits":62.84,"ratio_exprimes_votants":100.0},{"code_region":"84","libelle_region":"Auvergne-Rhône-Alpes","code_departement":"43","libelle_departement":"Haute-Loire","code_commune":"43168","libelle_commune":"Saint-Arcons-De-Barges","inscrits":131,"abstentions":51,"votants":80,"blancs":1,"nuls":1,"exprimes":78,"ratio_abstentions_inscrits":38.93,"ratio_votants_inscrits":61.07,"ratio_exprimes_votants":97.5},{"code_region":"84","libelle_region":"Auvergne-Rhône-Alpes","code_departement":"43","libelle_departement":"Haute-Loire","code_commune":"43169","libelle_commune":"Saint-Austremoine","inscrits":63,"abstentions":26,"votants":37,"blancs":2,"nuls":1,"exprimes":34,"ratio_abstentions_inscrits":41.27,"ratio_votants_inscrits":58.73,"ratio_exprimes_votants":91.89},{"code_region":"84","libelle_region":"Auvergne-Rhône-Alpes","code_departement":"43","libelle_departement":"Haute-Loire","code_commune":"43170","libelle_commune":"Saint-Beauzire","inscrits":295,"abstentions":120,"votants":175,"blancs":5,"nuls":2,"exprimes":168,"ratio_abstentions_inscrits":40.68,"ratio_votants_inscrits":59.32,"ratio_exprimes_votants":96.0},{"code_region":"84","libelle_region":"Auvergne-Rhône-Alpes","code_departement":"43","libelle_departement":"Haute-Loire","code_commune":"43171","libelle_commune":"Saint-Bérain","inscrits":100,"abstentions":30,"votants":70,"blancs":0,"nuls":1,"exprimes":69,"ratio_abstentions_inscrits":30.0,"ratio_votants_inscrits":70.0,"ratio_exprimes_votants":98.57},{"code_region":"84","libelle_region":"Auvergne-Rhône-Alpes","code_departement":"43","libelle_departement":"Haute-Loire","code_commune":"43172","libelle_commune":"Saint-Bonnet-Le-Froid","inscrits":201,"abstentions":79,"votants":122,"blancs":4,"nuls":2,"exprimes":116,"ratio_abstentions_inscrits":39.3,"ratio_votants_inscrits":60.7,"ratio_exprimes_votants":95.08},{"code_region":"84","libelle_region":"Auvergne-Rhône-Alpes","code_departement":"43","libelle_departement":"Haute-Loire","code_commune":"43173","libelle_commune":"Saint-Christophe-D'Allier","inscrits":109,"abstentions":38,"votants":71,"blancs":0,"nuls":3,"exprimes":68,"ratio_abstentions_inscrits":34.86,"ratio_votants_inscrits":65.14,"ratio_exprimes_votants":95.77},{"code_region":"84","libelle_region":"Auvergne-Rhône-Alpes","code_departement":"43","libelle_departement":"Haute-Loire","code_commune":"43174","libelle_commune":"Saint-Christophe-Sur-Dolaison","inscrits":794,"abstentions":305,"votants":489,"blancs":10,"nuls":7,"exprimes":472,"ratio_abstentions_inscrits":38.41,"ratio_votants_inscrits":61.59,"ratio_exprimes_votants":96.52},{"code_region":"84","libelle_region":"Auvergne-Rhône-Alpes","code_departement":"43","libelle_departement":"Haute-Loire","code_commune":"43175","libelle_commune":"Saint-Cirgues","inscrits":139,"abstentions":52,"votants":87,"blancs":3,"nuls":3,"exprimes":81,"ratio_abstentions_inscrits":37.41,"ratio_votants_inscrits":62.59,"ratio_exprimes_votants":93.1},{"code_region":"84","libelle_region":"Auvergne-Rhône-Alpes","code_departement":"43","libelle_departement":"Haute-Loire","code_commune":"43177","libelle_commune":"Saint-Didier-En-Velay","inscrits":2803,"abstentions":1200,"votants":1603,"blancs":36,"nuls":29,"exprimes":1538,"ratio_abstentions_inscrits":42.81,"ratio_votants_inscrits":57.19,"ratio_exprimes_votants":95.95},{"code_region":"84","libelle_region":"Auvergne-Rhône-Alpes","code_departement":"43","libelle_departement":"Haute-Loire","code_commune":"43178","libelle_commune":"Saint-Didier-Sur-Doulon","inscrits":206,"abstentions":62,"votants":144,"blancs":3,"nuls":4,"exprimes":137,"ratio_abstentions_inscrits":30.1,"ratio_votants_inscrits":69.9,"ratio_exprimes_votants":95.14},{"code_region":"84","libelle_region":"Auvergne-Rhône-Alpes","code_departement":"43","libelle_departement":"Haute-Loire","code_commune":"43180","libelle_commune":"Saint-Etienne-Du-Vigan","inscrits":109,"abstentions":40,"votants":69,"blancs":4,"nuls":0,"exprimes":65,"ratio_abstentions_inscrits":36.7,"ratio_votants_inscrits":63.3,"ratio_exprimes_votants":94.2},{"code_region":"84","libelle_region":"Auvergne-Rhône-Alpes","code_departement":"43","libelle_departement":"Haute-Loire","code_commune":"43181","libelle_commune":"Saint-Etienne-Lardeyrol","inscrits":642,"abstentions":274,"votants":368,"blancs":3,"nuls":8,"exprimes":357,"ratio_abstentions_inscrits":42.68,"ratio_votants_inscrits":57.32,"ratio_exprimes_votants":97.01},{"code_region":"84","libelle_region":"Auvergne-Rhône-Alpes","code_departement":"43","libelle_departement":"Haute-Loire","code_commune":"43182","libelle_commune":"Saint-Etienne-Sur-Blesle","inscrits":62,"abstentions":20,"votants":42,"blancs":3,"nuls":1,"exprimes":38,"ratio_abstentions_inscrits":32.26,"ratio_votants_inscrits":67.74,"ratio_exprimes_votants":90.48},{"code_region":"84","libelle_region":"Auvergne-Rhône-Alpes","code_departement":"43","libelle_departement":"Haute-Loire","code_commune":"43183","libelle_commune":"Sainte-Eugénie-De-Villeneuve","inscrits":96,"abstentions":31,"votants":65,"blancs":1,"nuls":6,"exprimes":58,"ratio_abstentions_inscrits":32.29,"ratio_votants_inscrits":67.71,"ratio_exprimes_votants":89.23},{"code_region":"84","libelle_region":"Auvergne-Rhône-Alpes","code_departement":"43","libelle_departement":"Haute-Loire","code_commune":"43184","libelle_commune":"Saint-Ferréol-D'Auroure","inscrits":1949,"abstentions":773,"votants":1176,"blancs":18,"nuls":21,"exprimes":1137,"ratio_abstentions_inscrits":39.66,"ratio_votants_inscrits":60.34,"ratio_exprimes_votants":96.68},{"code_region":"84","libelle_region":"Auvergne-Rhône-Alpes","code_departement":"43","libelle_departement":"Haute-Loire","code_commune":"43185","libelle_commune":"Sainte-Florine","inscrits":2386,"abstentions":1224,"votants":1162,"blancs":13,"nuls":34,"exprimes":1115,"ratio_abstentions_inscrits":51.3,"ratio_votants_inscrits":48.7,"ratio_exprimes_votants":95.96},{"code_region":"84","libelle_region":"Auvergne-Rhône-Alpes","code_departement":"43","libelle_departement":"Haute-Loire","code_commune":"43186","libelle_commune":"Saint-Front","inscrits":396,"abstentions":142,"votants":254,"blancs":6,"nuls":4,"exprimes":244,"ratio_abstentions_inscrits":35.86,"ratio_votants_inscrits":64.14,"ratio_exprimes_votants":96.06},{"code_region":"84","libelle_region":"Auvergne-Rhône-Alpes","code_departement":"43","libelle_departement":"Haute-Loire","code_commune":"43187","libelle_commune":"Saint-Geneys-Près-Saint-Paulien","inscrits":270,"abstentions":100,"votants":170,"blancs":5,"nuls":4,"exprimes":161,"ratio_abstentions_inscrits":37.04,"ratio_votants_inscrits":62.96,"ratio_exprimes_votants":94.71},{"code_region":"84","libelle_region":"Auvergne-Rhône-Alpes","code_departement":"43","libelle_departement":"Haute-Loire","code_commune":"43188","libelle_commune":"Saint-Georges-D'Aurac","inscrits":351,"abstentions":187,"votants":164,"blancs":5,"nuls":2,"exprimes":157,"ratio_abstentions_inscrits":53.28,"ratio_votants_inscrits":46.72,"ratio_exprimes_votants":95.73},{"code_region":"84","libelle_region":"Auvergne-Rhône-Alpes","code_departement":"43","libelle_departement":"Haute-Loire","code_commune":"43189","libelle_commune":"Saint-Georges-Lagricol","inscrits":429,"abstentions":178,"votants":251,"blancs":6,"nuls":5,"exprimes":240,"ratio_abstentions_inscrits":41.49,"ratio_votants_inscrits":58.51,"ratio_exprimes_votants":95.62},{"code_region":"84","libelle_region":"Auvergne-Rhône-Alpes","code_departement":"43","libelle_departement":"Haute-Loire","code_commune":"43190","libelle_commune":"Saint-Germain-Laprade","inscrits":2956,"abstentions":1256,"votants":1700,"blancs":34,"nuls":32,"exprimes":1634,"ratio_abstentions_inscrits":42.49,"ratio_votants_inscrits":57.51,"ratio_exprimes_votants":96.12},{"code_region":"84","libelle_region":"Auvergne-Rhône-Alpes","code_departement":"43","libelle_departement":"Haute-Loire","code_commune":"43191","libelle_commune":"Saint-Géron","inscrits":220,"abstentions":91,"votants":129,"blancs":6,"nuls":3,"exprimes":120,"ratio_abstentions_inscrits":41.36,"ratio_votants_inscrits":58.64,"ratio_exprimes_votants":93.02},{"code_region":"84","libelle_region":"Auvergne-Rhône-Alpes","code_departement":"43","libelle_departement":"Haute-Loire","code_commune":"43192","libelle_commune":"Saint-Haon","inscrits":289,"abstentions":119,"votants":170,"blancs":1,"nuls":8,"exprimes":161,"ratio_abstentions_inscrits":41.18,"ratio_votants_inscrits":58.82,"ratio_exprimes_votants":94.71},{"code_region":"84","libelle_region":"Auvergne-Rhône-Alpes","code_departement":"43","libelle_departement":"Haute-Loire","code_commune":"43193","libelle_commune":"Saint-Hilaire","inscrits":158,"abstentions":54,"votants":104,"blancs":3,"nuls":3,"exprimes":98,"ratio_abstentions_inscrits":34.18,"ratio_votants_inscrits":65.82,"ratio_exprimes_votants":94.23},{"code_region":"84","libelle_region":"Auvergne-Rhône-Alpes","code_departement":"43","libelle_departement":"Haute-Loire","code_commune":"43194","libelle_commune":"Saint-Hostien","inscrits":558,"abstentions":226,"votants":332,"blancs":5,"nuls":5,"exprimes":322,"ratio_abstentions_inscrits":40.5,"ratio_votants_inscrits":59.5,"ratio_exprimes_votants":96.99},{"code_region":"84","libelle_region":"Auvergne-Rhône-Alpes","code_departement":"43","libelle_departement":"Haute-Loire","code_commune":"43195","libelle_commune":"Saint-Ilpize","inscrits":216,"abstentions":85,"votants":131,"blancs":2,"nuls":1,"exprimes":128,"ratio_abstentions_inscrits":39.35,"ratio_votants_inscrits":60.65,"ratio_exprimes_votants":97.71},{"code_region":"84","libelle_region":"Auvergne-Rhône-Alpes","code_departement":"43","libelle_departement":"Haute-Loire","code_commune":"43196","libelle_commune":"Saint-Jean-D'Aubrigoux","inscrits":182,"abstentions":77,"votants":105,"blancs":1,"nuls":3,"exprimes":101,"ratio_abstentions_inscrits":42.31,"ratio_votants_inscrits":57.69,"ratio_exprimes_votants":96.19},{"code_region":"84","libelle_region":"Auvergne-Rhône-Alpes","code_departement":"43","libelle_departement":"Haute-Loire","code_commune":"43197","libelle_commune":"Saint-Jean-De-Nay","inscrits":322,"abstentions":130,"votants":192,"blancs":4,"nuls":6,"exprimes":182,"ratio_abstentions_inscrits":40.37,"ratio_votants_inscrits":59.63,"ratio_exprimes_votants":94.79},{"code_region":"84","libelle_region":"Auvergne-Rhône-Alpes","code_departement":"43","libelle_departement":"Haute-Loire","code_commune":"43198","libelle_commune":"Saint-Jean-Lachalm","inscrits":278,"abstentions":112,"votants":166,"blancs":4,"nuls":9,"exprimes":153,"ratio_abstentions_inscrits":40.29,"ratio_votants_inscrits":59.71,"ratio_exprimes_votants":92.17},{"code_region":"84","libelle_region":"Auvergne-Rhône-Alpes","code_departement":"43","libelle_departement":"Haute-Loire","code_commune":"43199","libelle_commune":"Saint-Jeures","inscrits":883,"abstentions":390,"votants":493,"blancs":2,"nuls":27,"exprimes":464,"ratio_abstentions_inscrits":44.17,"ratio_votants_inscrits":55.83,"ratio_exprimes_votants":94.12},{"code_region":"84","libelle_region":"Auvergne-Rhône-Alpes","code_departement":"43","libelle_departement":"Haute-Loire","code_commune":"43200","libelle_commune":"Saint-Julien-Chapteuil","inscrits":1592,"abstentions":669,"votants":923,"blancs":17,"nuls":20,"exprimes":886,"ratio_abstentions_inscrits":42.02,"ratio_votants_inscrits":57.98,"ratio_exprimes_votants":95.99},{"code_region":"84","libelle_region":"Auvergne-Rhône-Alpes","code_departement":"43","libelle_departement":"Haute-Loire","code_commune":"43201","libelle_commune":"Saint-Julien-D'Ance","inscrits":252,"abstentions":122,"votants":130,"blancs":3,"nuls":4,"exprimes":123,"ratio_abstentions_inscrits":48.41,"ratio_votants_inscrits":51.59,"ratio_exprimes_votants":94.62},{"code_region":"84","libelle_region":"Auvergne-Rhône-Alpes","code_departement":"43","libelle_departement":"Haute-Loire","code_commune":"43202","libelle_commune":"Saint-Julien-Des-Chazes","inscrits":89,"abstentions":31,"votants":58,"blancs":0,"nuls":3,"exprimes":55,"ratio_abstentions_inscrits":34.83,"ratio_votants_inscrits":65.17,"ratio_exprimes_votants":94.83},{"code_region":"84","libelle_region":"Auvergne-Rhône-Alpes","code_departement":"43","libelle_departement":"Haute-Loire","code_commune":"43203","libelle_commune":"Saint-Julien-Du-Pinet","inscrits":428,"abstentions":134,"votants":294,"blancs":5,"nuls":5,"exprimes":284,"ratio_abstentions_inscrits":31.31,"ratio_votants_inscrits":68.69,"ratio_exprimes_votants":96.6},{"code_region":"84","libelle_region":"Auvergne-Rhône-Alpes","code_departement":"43","libelle_departement":"Haute-Loire","code_commune":"43204","libelle_commune":"Saint-Julien-Molhesabate","inscrits":160,"abstentions":63,"votants":97,"blancs":6,"nuls":3,"exprimes":88,"ratio_abstentions_inscrits":39.38,"ratio_votants_inscrits":60.62,"ratio_exprimes_votants":90.72},{"code_region":"84","libelle_region":"Auvergne-Rhône-Alpes","code_departement":"43","libelle_departement":"Haute-Loire","code_commune":"43205","libelle_commune":"Saint-Just-Malmont","inscrits":3276,"abstentions":1361,"votants":1915,"blancs":50,"nuls":32,"exprimes":1833,"ratio_abstentions_inscrits":41.54,"ratio_votants_inscrits":58.46,"ratio_exprimes_votants":95.72},{"code_region":"84","libelle_region":"Auvergne-Rhône-Alpes","code_departement":"43","libelle_departement":"Haute-Loire","code_commune":"43206","libelle_commune":"Saint-Just-Près-Brioude","inscrits":391,"abstentions":170,"votants":221,"blancs":7,"nuls":4,"exprimes":210,"ratio_abstentions_inscrits":43.48,"ratio_votants_inscrits":56.52,"ratio_exprimes_votants":95.02},{"code_region":"84","libelle_region":"Auvergne-Rhône-Alpes","code_departement":"43","libelle_departement":"Haute-Loire","code_commune":"43207","libelle_commune":"Saint-Laurent-Chabreuges","inscrits":212,"abstentions":89,"votants":123,"blancs":1,"nuls":4,"exprimes":118,"ratio_abstentions_inscrits":41.98,"ratio_votants_inscrits":58.02,"ratio_exprimes_votants":95.93},{"code_region":"84","libelle_region":"Auvergne-Rhône-Alpes","code_departement":"43","libelle_departement":"Haute-Loire","code_commune":"43208","libelle_commune":"Sainte-Marguerite","inscrits":44,"abstentions":11,"votants":33,"blancs":1,"nuls":3,"exprimes":29,"ratio_abstentions_inscrits":25.0,"ratio_votants_inscrits":75.0,"ratio_exprimes_votants":87.88},{"code_region":"84","libelle_region":"Auvergne-Rhône-Alpes","code_departement":"43","libelle_departement":"Haute-Loire","code_commune":"43210","libelle_commune":"Saint-Martin-De-Fugères","inscrits":241,"abstentions":87,"votants":154,"blancs":2,"nuls":2,"exprimes":150,"ratio_abstentions_inscrits":36.1,"ratio_votants_inscrits":63.9,"ratio_exprimes_votants":97.4},{"code_region":"84","libelle_region":"Auvergne-Rhône-Alpes","code_departement":"43","libelle_departement":"Haute-Loire","code_commune":"43211","libelle_commune":"Saint-Maurice-De-Lignon","inscrits":1977,"abstentions":871,"votants":1106,"blancs":24,"nuls":15,"exprimes":1067,"ratio_abstentions_inscrits":44.06,"ratio_votants_inscrits":55.94,"ratio_exprimes_votants":96.47},{"code_region":"84","libelle_region":"Auvergne-Rhône-Alpes","code_departement":"43","libelle_departement":"Haute-Loire","code_commune":"43212","libelle_commune":"Saint-Pal-De-Chalencon","inscrits":903,"abstentions":442,"votants":461,"blancs":8,"nuls":6,"exprimes":447,"ratio_abstentions_inscrits":48.95,"ratio_votants_inscrits":51.05,"ratio_exprimes_votants":96.96},{"code_region":"84","libelle_region":"Auvergne-Rhône-Alpes","code_departement":"43","libelle_departement":"Haute-Loire","code_commune":"43213","libelle_commune":"Saint-Pal-De-Mons","inscrits":1822,"abstentions":779,"votants":1043,"blancs":13,"nuls":12,"exprimes":1018,"ratio_abstentions_inscrits":42.76,"ratio_votants_inscrits":57.24,"ratio_exprimes_votants":97.6},{"code_region":"84","libelle_region":"Auvergne-Rhône-Alpes","code_departement":"43","libelle_departement":"Haute-Loire","code_commune":"43214","libelle_commune":"Saint-Pal-De-Senouire","inscrits":108,"abstentions":35,"votants":73,"blancs":3,"nuls":4,"exprimes":66,"ratio_abstentions_inscrits":32.41,"ratio_votants_inscrits":67.59,"ratio_exprimes_votants":90.41},{"code_region":"84","libelle_region":"Auvergne-Rhône-Alpes","code_departement":"43","libelle_departement":"Haute-Loire","code_commune":"43215","libelle_commune":"Saint-Paul-De-Tartas","inscrits":211,"abstentions":74,"votants":137,"blancs":4,"nuls":1,"exprimes":132,"ratio_abstentions_inscrits":35.07,"ratio_votants_inscrits":64.93,"ratio_exprimes_votants":96.35},{"code_region":"84","libelle_region":"Auvergne-Rhône-Alpes","code_departement":"43","libelle_departement":"Haute-Loire","code_commune":"43216","libelle_commune":"Saint-Paulien","inscrits":1746,"abstentions":737,"votants":1009,"blancs":24,"nuls":21,"exprimes":964,"ratio_abstentions_inscrits":42.21,"ratio_votants_inscrits":57.79,"ratio_exprimes_votants":95.54},{"code_region":"84","libelle_region":"Auvergne-Rhône-Alpes","code_departement":"43","libelle_departement":"Haute-Loire","code_commune":"43217","libelle_commune":"Saint-Pierre-Du-Champ","inscrits":508,"abstentions":203,"votants":305,"blancs":4,"nuls":10,"exprimes":291,"ratio_abstentions_inscrits":39.96,"ratio_votants_inscrits":60.04,"ratio_exprimes_votants":95.41},{"code_region":"84","libelle_region":"Auvergne-Rhône-Alpes","code_departement":"43","libelle_departement":"Haute-Loire","code_commune":"43218","libelle_commune":"Saint-Pierre-Eynac","inscrits":994,"abstentions":395,"votants":599,"blancs":18,"nuls":14,"exprimes":567,"ratio_abstentions_inscrits":39.74,"ratio_votants_inscrits":60.26,"ratio_exprimes_votants":94.66},{"code_region":"84","libelle_region":"Auvergne-Rhône-Alpes","code_departement":"43","libelle_departement":"Haute-Loire","code_commune":"43219","libelle_commune":"Saint-Préjet-Armandon","inscrits":100,"abstentions":36,"votants":64,"blancs":1,"nuls":2,"exprimes":61,"ratio_abstentions_inscrits":36.0,"ratio_votants_inscrits":64.0,"ratio_exprimes_votants":95.31},{"code_region":"84","libelle_region":"Auvergne-Rhône-Alpes","code_departement":"43","libelle_departement":"Haute-Loire","code_commune":"43220","libelle_commune":"Saint-Préjet-D'Allier","inscrits":175,"abstentions":79,"votants":96,"blancs":2,"nuls":2,"exprimes":92,"ratio_abstentions_inscrits":45.14,"ratio_votants_inscrits":54.86,"ratio_exprimes_votants":95.83},{"code_region":"84","libelle_region":"Auvergne-Rhône-Alpes","code_departement":"43","libelle_departement":"Haute-Loire","code_commune":"43221","libelle_commune":"Saint-Privat-D'Allier","inscrits":379,"abstentions":157,"votants":222,"blancs":3,"nuls":2,"exprimes":217,"ratio_abstentions_inscrits":41.42,"ratio_votants_inscrits":58.58,"ratio_exprimes_votants":97.75},{"code_region":"84","libelle_region":"Auvergne-Rhône-Alpes","code_departement":"43","libelle_departement":"Haute-Loire","code_commune":"43222","libelle_commune":"Saint-Privat-Du-Dragon","inscrits":157,"abstentions":53,"votants":104,"blancs":6,"nuls":7,"exprimes":91,"ratio_abstentions_inscrits":33.76,"ratio_votants_inscrits":66.24,"ratio_exprimes_votants":87.5},{"code_region":"84","libelle_region":"Auvergne-Rhône-Alpes","code_departement":"43","libelle_departement":"Haute-Loire","code_commune":"43223","libelle_commune":"Saint-Romain-Lachalm","inscrits":939,"abstentions":344,"votants":595,"blancs":18,"nuls":9,"exprimes":568,"ratio_abstentions_inscrits":36.63,"ratio_votants_inscrits":63.37,"ratio_exprimes_votants":95.46},{"code_region":"84","libelle_region":"Auvergne-Rhône-Alpes","code_departement":"43","libelle_departement":"Haute-Loire","code_commune":"43224","libelle_commune":"Sainte-Sigolène","inscrits":4525,"abstentions":2319,"votants":2206,"blancs":36,"nuls":41,"exprimes":2129,"ratio_abstentions_inscrits":51.25,"ratio_votants_inscrits":48.75,"ratio_exprimes_votants":96.51},{"code_region":"84","libelle_region":"Auvergne-Rhône-Alpes","code_departement":"43","libelle_departement":"Haute-Loire","code_commune":"43225","libelle_commune":"Saint-Vénérand","inscrits":53,"abstentions":13,"votants":40,"blancs":0,"nuls":0,"exprimes":40,"ratio_abstentions_inscrits":24.53,"ratio_votants_inscrits":75.47,"ratio_exprimes_votants":100.0},{"code_region":"84","libelle_region":"Auvergne-Rhône-Alpes","code_departement":"43","libelle_departement":"Haute-Loire","code_commune":"43226","libelle_commune":"Saint-Vert","inscrits":100,"abstentions":47,"votants":53,"blancs":0,"nuls":0,"exprimes":53,"ratio_abstentions_inscrits":47.0,"ratio_votants_inscrits":53.0,"ratio_exprimes_votants":100.0},{"code_region":"84","libelle_region":"Auvergne-Rhône-Alpes","code_departement":"43","libelle_departement":"Haute-Loire","code_commune":"43227","libelle_commune":"Saint-Victor-Malescours","inscrits":630,"abstentions":224,"votants":406,"blancs":5,"nuls":9,"exprimes":392,"ratio_abstentions_inscrits":35.56,"ratio_votants_inscrits":64.44,"ratio_exprimes_votants":96.55},{"code_region":"84","libelle_region":"Auvergne-Rhône-Alpes","code_departement":"43","libelle_departement":"Haute-Loire","code_commune":"43228","libelle_commune":"Saint-Victor-Sur-Arlanc","inscrits":109,"abstentions":46,"votants":63,"blancs":1,"nuls":3,"exprimes":59,"ratio_abstentions_inscrits":42.2,"ratio_votants_inscrits":57.8,"ratio_exprimes_votants":93.65},{"code_region":"84","libelle_region":"Auvergne-Rhône-Alpes","code_departement":"43","libelle_departement":"Haute-Loire","code_commune":"43229","libelle_commune":"Saint-Vidal","inscrits":451,"abstentions":153,"votants":298,"blancs":7,"nuls":6,"exprimes":285,"ratio_abstentions_inscrits":33.92,"ratio_votants_inscrits":66.08,"ratio_exprimes_votants":95.64},{"code_region":"84","libelle_region":"Auvergne-Rhône-Alpes","code_departement":"43","libelle_departement":"Haute-Loire","code_commune":"43230","libelle_commune":"Saint-Vincent","inscrits":893,"abstentions":389,"votants":504,"blancs":8,"nuls":6,"exprimes":490,"ratio_abstentions_inscrits":43.56,"ratio_votants_inscrits":56.44,"ratio_exprimes_votants":97.22},{"code_region":"84","libelle_region":"Auvergne-Rhône-Alpes","code_departement":"43","libelle_departement":"Haute-Loire","code_commune":"43231","libelle_commune":"Salettes","inscrits":195,"abstentions":60,"votants":135,"blancs":1,"nuls":2,"exprimes":132,"ratio_abstentions_inscrits":30.77,"ratio_votants_inscrits":69.23,"ratio_exprimes_votants":97.78},{"code_region":"84","libelle_region":"Auvergne-Rhône-Alpes","code_departement":"43","libelle_departement":"Haute-Loire","code_commune":"43232","libelle_commune":"Salzuit","inscrits":266,"abstentions":115,"votants":151,"blancs":1,"nuls":4,"exprimes":146,"ratio_abstentions_inscrits":43.23,"ratio_votants_inscrits":56.77,"ratio_exprimes_votants":96.69},{"code_region":"84","libelle_region":"Auvergne-Rhône-Alpes","code_departement":"43","libelle_departement":"Haute-Loire","code_commune":"43233","libelle_commune":"Sanssac-L'Eglise","inscrits":919,"abstentions":350,"votants":569,"blancs":6,"nuls":5,"exprimes":558,"ratio_abstentions_inscrits":38.08,"ratio_votants_inscrits":61.92,"ratio_exprimes_votants":98.07},{"code_region":"84","libelle_region":"Auvergne-Rhône-Alpes","code_departement":"43","libelle_departement":"Haute-Loire","code_commune":"43234","libelle_commune":"Saugues","inscrits":1429,"abstentions":645,"votants":784,"blancs":20,"nuls":19,"exprimes":745,"ratio_abstentions_inscrits":45.14,"ratio_votants_inscrits":54.86,"ratio_exprimes_votants":95.03},{"code_region":"84","libelle_region":"Auvergne-Rhône-Alpes","code_departement":"43","libelle_departement":"Haute-Loire","code_commune":"43236","libelle_commune":"La Séauve-Sur-Semène","inscrits":1007,"abstentions":415,"votants":592,"blancs":3,"nuls":10,"exprimes":579,"ratio_abstentions_inscrits":41.21,"ratio_votants_inscrits":58.79,"ratio_exprimes_votants":97.8},{"code_region":"84","libelle_region":"Auvergne-Rhône-Alpes","code_departement":"43","libelle_departement":"Haute-Loire","code_commune":"43237","libelle_commune":"Sembadel","inscrits":253,"abstentions":97,"votants":156,"blancs":2,"nuls":6,"exprimes":148,"ratio_abstentions_inscrits":38.34,"ratio_votants_inscrits":61.66,"ratio_exprimes_votants":94.87},{"code_region":"84","libelle_region":"Auvergne-Rhône-Alpes","code_departement":"43","libelle_departement":"Haute-Loire","code_commune":"43238","libelle_commune":"Séneujols","inscrits":314,"abstentions":84,"votants":230,"blancs":7,"nuls":12,"exprimes":211,"ratio_abstentions_inscrits":26.75,"ratio_votants_inscrits":73.25,"ratio_exprimes_votants":91.74},{"code_region":"84","libelle_region":"Auvergne-Rhône-Alpes","code_departement":"43","libelle_departement":"Haute-Loire","code_commune":"43239","libelle_commune":"Siaugues-Sainte-Marie","inscrits":693,"abstentions":284,"votants":409,"blancs":10,"nuls":16,"exprimes":383,"ratio_abstentions_inscrits":40.98,"ratio_votants_inscrits":59.02,"ratio_exprimes_votants":93.64},{"code_region":"84","libelle_region":"Auvergne-Rhône-Alpes","code_departement":"43","libelle_departement":"Haute-Loire","code_commune":"43240","libelle_commune":"Solignac-Sous-Roche","inscrits":243,"abstentions":96,"votants":147,"blancs":5,"nuls":4,"exprimes":138,"ratio_abstentions_inscrits":39.51,"ratio_votants_inscrits":60.49,"ratio_exprimes_votants":93.88},{"code_region":"84","libelle_region":"Auvergne-Rhône-Alpes","code_departement":"43","libelle_departement":"Haute-Loire","code_commune":"43241","libelle_commune":"Solignac-Sur-Loire","inscrits":1018,"abstentions":390,"votants":628,"blancs":11,"nuls":14,"exprimes":603,"ratio_abstentions_inscrits":38.31,"ratio_votants_inscrits":61.69,"ratio_exprimes_votants":96.02},{"code_region":"84","libelle_region":"Auvergne-Rhône-Alpes","code_departement":"43","libelle_departement":"Haute-Loire","code_commune":"43242","libelle_commune":"Tailhac","inscrits":51,"abstentions":16,"votants":35,"blancs":2,"nuls":0,"exprimes":33,"ratio_abstentions_inscrits":31.37,"ratio_votants_inscrits":68.63,"ratio_exprimes_votants":94.29},{"code_region":"84","libelle_region":"Auvergne-Rhône-Alpes","code_departement":"43","libelle_departement":"Haute-Loire","code_commune":"43244","libelle_commune":"Tence","inscrits":2669,"abstentions":1181,"votants":1488,"blancs":45,"nuls":29,"exprimes":1414,"ratio_abstentions_inscrits":44.25,"ratio_votants_inscrits":55.75,"ratio_exprimes_votants":95.03},{"code_region":"84","libelle_region":"Auvergne-Rhône-Alpes","code_departement":"43","libelle_departement":"Haute-Loire","code_commune":"43245","libelle_commune":"Thoras","inscrits":233,"abstentions":94,"votants":139,"blancs":3,"nuls":7,"exprimes":129,"ratio_abstentions_inscrits":40.34,"ratio_votants_inscrits":59.66,"ratio_exprimes_votants":92.81},{"code_region":"84","libelle_region":"Auvergne-Rhône-Alpes","code_departement":"43","libelle_departement":"Haute-Loire","code_commune":"43246","libelle_commune":"Tiranges","inscrits":411,"abstentions":153,"votants":258,"blancs":8,"nuls":2,"exprimes":248,"ratio_abstentions_inscrits":37.23,"ratio_votants_inscrits":62.77,"ratio_exprimes_votants":96.12},{"code_region":"84","libelle_region":"Auvergne-Rhône-Alpes","code_departement":"43","libelle_departement":"Haute-Loire","code_commune":"43247","libelle_commune":"Torsiac","inscrits":65,"abstentions":26,"votants":39,"blancs":1,"nuls":3,"exprimes":35,"ratio_abstentions_inscrits":40.0,"ratio_votants_inscrits":60.0,"ratio_exprimes_votants":89.74},{"code_region":"84","libelle_region":"Auvergne-Rhône-Alpes","code_departement":"43","libelle_departement":"Haute-Loire","code_commune":"43249","libelle_commune":"Valprivas","inscrits":467,"abstentions":148,"votants":319,"blancs":5,"nuls":12,"exprimes":302,"ratio_abstentions_inscrits":31.69,"ratio_votants_inscrits":68.31,"ratio_exprimes_votants":94.67},{"code_region":"84","libelle_region":"Auvergne-Rhône-Alpes","code_departement":"43","libelle_departement":"Haute-Loire","code_commune":"43250","libelle_commune":"Vals-Le-Chastel","inscrits":43,"abstentions":18,"votants":25,"blancs":1,"nuls":0,"exprimes":24,"ratio_abstentions_inscrits":41.86,"ratio_votants_inscrits":58.14,"ratio_exprimes_votants":96.0},{"code_region":"84","libelle_region":"Auvergne-Rhône-Alpes","code_departement":"43","libelle_departement":"Haute-Loire","code_commune":"43251","libelle_commune":"Vals-Près-Le-Puy","inscrits":2335,"abstentions":948,"votants":1387,"blancs":14,"nuls":28,"exprimes":1345,"ratio_abstentions_inscrits":40.6,"ratio_votants_inscrits":59.4,"ratio_exprimes_votants":96.97},{"code_region":"84","libelle_region":"Auvergne-Rhône-Alpes","code_departement":"43","libelle_departement":"Haute-Loire","code_commune":"43252","libelle_commune":"Varennes-Saint-Honorat","inscrits":34,"abstentions":12,"votants":22,"blancs":1,"nuls":1,"exprimes":20,"ratio_abstentions_inscrits":35.29,"ratio_votants_inscrits":64.71,"ratio_exprimes_votants":90.91},{"code_region":"84","libelle_region":"Auvergne-Rhône-Alpes","code_departement":"43","libelle_departement":"Haute-Loire","code_commune":"43253","libelle_commune":"Les Vastres","inscrits":228,"abstentions":111,"votants":117,"blancs":1,"nuls":3,"exprimes":113,"ratio_abstentions_inscrits":48.68,"ratio_votants_inscrits":51.32,"ratio_exprimes_votants":96.58},{"code_region":"84","libelle_region":"Auvergne-Rhône-Alpes","code_departement":"43","libelle_departement":"Haute-Loire","code_commune":"43254","libelle_commune":"Vazeilles-Limandre","inscrits":204,"abstentions":81,"votants":123,"blancs":2,"nuls":4,"exprimes":117,"ratio_abstentions_inscrits":39.71,"ratio_votants_inscrits":60.29,"ratio_exprimes_votants":95.12},{"code_region":"84","libelle_region":"Auvergne-Rhône-Alpes","code_departement":"43","libelle_departement":"Haute-Loire","code_commune":"43256","libelle_commune":"Venteuges","inscrits":323,"abstentions":149,"votants":174,"blancs":10,"nuls":10,"exprimes":154,"ratio_abstentions_inscrits":46.13,"ratio_votants_inscrits":53.87,"ratio_exprimes_votants":88.51},{"code_region":"84","libelle_region":"Auvergne-Rhône-Alpes","code_departement":"43","libelle_departement":"Haute-Loire","code_commune":"43257","libelle_commune":"Vergezac","inscrits":399,"abstentions":156,"votants":243,"blancs":8,"nuls":10,"exprimes":225,"ratio_abstentions_inscrits":39.1,"ratio_votants_inscrits":60.9,"ratio_exprimes_votants":92.59},{"code_region":"84","libelle_region":"Auvergne-Rhône-Alpes","code_departement":"43","libelle_departement":"Haute-Loire","code_commune":"43258","libelle_commune":"Vergongheon","inscrits":1381,"abstentions":712,"votants":669,"blancs":14,"nuls":21,"exprimes":634,"ratio_abstentions_inscrits":51.56,"ratio_votants_inscrits":48.44,"ratio_exprimes_votants":94.77},{"code_region":"84","libelle_region":"Auvergne-Rhône-Alpes","code_departement":"43","libelle_departement":"Haute-Loire","code_commune":"43259","libelle_commune":"Vernassal","inscrits":334,"abstentions":116,"votants":218,"blancs":3,"nuls":9,"exprimes":206,"ratio_abstentions_inscrits":34.73,"ratio_votants_inscrits":65.27,"ratio_exprimes_votants":94.5},{"code_region":"84","libelle_region":"Auvergne-Rhône-Alpes","code_departement":"43","libelle_departement":"Haute-Loire","code_commune":"43260","libelle_commune":"Le Vernet","inscrits":24,"abstentions":9,"votants":15,"blancs":0,"nuls":0,"exprimes":15,"ratio_abstentions_inscrits":37.5,"ratio_votants_inscrits":62.5,"ratio_exprimes_votants":100.0},{"code_region":"84","libelle_region":"Auvergne-Rhône-Alpes","code_departement":"43","libelle_departement":"Haute-Loire","code_commune":"43261","libelle_commune":"Vézézoux","inscrits":498,"abstentions":208,"votants":290,"blancs":10,"nuls":5,"exprimes":275,"ratio_abstentions_inscrits":41.77,"ratio_votants_inscrits":58.23,"ratio_exprimes_votants":94.83},{"code_region":"84","libelle_region":"Auvergne-Rhône-Alpes","code_departement":"43","libelle_departement":"Haute-Loire","code_commune":"43262","libelle_commune":"Vieille-Brioude","inscrits":1018,"abstentions":436,"votants":582,"blancs":14,"nuls":7,"exprimes":561,"ratio_abstentions_inscrits":42.83,"ratio_votants_inscrits":57.17,"ratio_exprimes_votants":96.39},{"code_region":"84","libelle_region":"Auvergne-Rhône-Alpes","code_departement":"43","libelle_departement":"Haute-Loire","code_commune":"43263","libelle_commune":"Vielprat","inscrits":78,"abstentions":29,"votants":49,"blancs":0,"nuls":2,"exprimes":47,"ratio_abstentions_inscrits":37.18,"ratio_votants_inscrits":62.82,"ratio_exprimes_votants":95.92},{"code_region":"84","libelle_region":"Auvergne-Rhône-Alpes","code_departement":"43","libelle_departement":"Haute-Loire","code_commune":"43264","libelle_commune":"Villeneuve-D'Allier","inscrits":252,"abstentions":120,"votants":132,"blancs":5,"nuls":0,"exprimes":127,"ratio_abstentions_inscrits":47.62,"ratio_votants_inscrits":52.38,"ratio_exprimes_votants":96.21},{"code_region":"84","libelle_region":"Auvergne-Rhône-Alpes","code_departement":"43","libelle_departement":"Haute-Loire","code_commune":"43265","libelle_commune":"Les Villettes","inscrits":1125,"abstentions":466,"votants":659,"blancs":14,"nuls":13,"exprimes":632,"ratio_abstentions_inscrits":41.42,"ratio_votants_inscrits":58.58,"ratio_exprimes_votants":95.9},{"code_region":"84","libelle_region":"Auvergne-Rhône-Alpes","code_departement":"43","libelle_departement":"Haute-Loire","code_commune":"43267","libelle_commune":"Vorey","inscrits":1221,"abstentions":528,"votants":693,"blancs":16,"nuls":12,"exprimes":665,"ratio_abstentions_inscrits":43.24,"ratio_votants_inscrits":56.76,"ratio_exprimes_votants":95.96},{"code_region":"84","libelle_region":"Auvergne-Rhône-Alpes","code_departement":"43","libelle_departement":"Haute-Loire","code_commune":"43268","libelle_commune":"Yssingeaux","inscrits":5852,"abstentions":2402,"votants":3450,"blancs":78,"nuls":74,"exprimes":3298,"ratio_abstentions_inscrits":41.05,"ratio_votants_inscrits":58.95,"ratio_exprimes_votants":95.59}]